Workbook
Name Slicer_product: #N/A
Name account: accounts!$A$2:$F$86
Name accounts: accounts!$1:$86
Name deal: pipeline!$E:$E
Name products: products!$A$1:$C$8
Name sales: 'sales teams'!$A$2:$C$36

Sheet pivot table
A1: 1.Number of Deals
A3: Count of opportunity_id
A4: 6117 | B4: =GETPIVOTDATA("opportunity_id",$A$3) -> 6117
A6: 2. Total revenue
A7: Sum of revenue | I7: 15004002
A8: 15004002 | B8: =GETPIVOTDATA("revenue",$A$7) -> 15004002
A11: 3.How is each sales team performing compared to the rest?
A12: Row Labels | B12: Sum of revenue
A13: Cara Losch | B13: 1739327
A14: Corliss Cosme | B14: 569695.77
A15: Garret Kinder | B15: 273585.39
A16: Rosie Papadopoulos | B16: 293414.02
A17: Violet Mclelland | B17: 446568.79
A18: Wilburn Farren | B18: 156063.06
A19: Celia Rouche | B19: 2638097.2
A20: Elease Gluck | B20: 338646.86
A21: Hayden Neloms | B21: 444544.2
A22: Markita Hansen | B22: 636848.2
A23: Rosalina Dieter | B23: 285821.05
A24: Vicki Laflamme | B24: 932236.87
... A48: Zane Levy | B48: 612370.94
A51: 4.Are any sales agents lagging behind?
A52: Row Labels | B52: Sum of revenue
A53: Vicki Laflamme | B53: 932236.87
A54: Kary Hendrixson | B54: 855578.41
A55: Anna Snelling | B55: 776091.45
A56: Kami Bicknell | B56: 724775.96
A57: Markita Hansen | B57: 636848.2
A58: Maureen Marcano | B58: 630663.44
A59: Zane Levy | B59: 612370.94
A60: Darcel Schlecht | B60: 576633.18
A61: Corliss Cosme | B61: 569695.77
A62: Versie Hillebrand | B62: 560647.45
A63: Lajuana Vencill | B63: 551473.89
A64: Jonathan Berthelot | B64: 533099.24
... A82: Wilburn Farren | B82: 156063.06

Sheet pivot table 2
A1: 5.Can you identify any quarter-over-quarter trends?
A2: Row Labels | B2: Sum of revenue
A3: Qtr1 | B3: 1336991.4
A4: Qtr2 | B4: 4265390.8
A5: Qtr3 | B5: 4143151.8
A6: Qtr4 | B6: 4182293.5
A15: 6.Do any products have better win rates?
A16: Count of opportunity_id | B16: Column Labels
A17: Row Labels | B17: Won | C17: Prospecting | D17: Lost | E17: Engaging | F17: Grand Total
A18: GTX Basic | B18: 915 | C18: 29 | D18: 521 | E18: 98 | F18: 1563
A19: MG Special | B19: 793 | C19: 41 | D19: 430 | E19: 95 | F19: 1359
A20: MG Advanced | B20: 654 | C20: 25 | D20: 430 | E20: 72 | F20: 1181
A21: GTX Plus Basic | B21: 653 | C21: 20 | D21: 398 | E21: 97 | F21: 1168
A22: GTX Plus Pro | B22: 479 | C22: 14 | D22: 266 | E22: 55 | F22: 814
A23: GTK 500 | B23: 15 | D23: 10 | E23: 7 | F23: 32
A27: 7. sales by product
A28: Row Labels | B28: Sum of revenue
A29: GTX Basic | B29: 4121351.3
A30: MG Advanced | B30: 3094260.9
A31: GTX Plus Basic | B31: 2911772.2
A32: MG Special | B32: 2731859.3
A33: GTX Plus Pro | B33: 2016191.4
A34: GTK 500 | B34: 128566.87 | K34: 3348224
K35: 2650522.8
K36: 2638097.2
A37: 8.Sales by manager | K37: 2365197.7
A38: Row Labels | B38: Sum of revenue | K38: 2262633.1
A39: Summer Sewald | B39: 3348224 | K39: 1739327
A40: Dustin Brinkmann | B40: 2650522.8
A41: Celia Rouche | B41: 2638097.2
A42: Melvin Marxen | B42: 2365197.7
A43: Rocco Neubert | B43: 2262633.1
A44: Cara Losch | B44: 1739327

Sheet Dashboard

Sheet pipeline
A1: opportunity_id | B1: sales_agent | C1: product | D1: account | E1: deal_stage | F1: engage_date | G1: close_date | H1: close_value | I1: sectors | J1: year_established | K1: revenue | L1: employees | M1: office_location | N1: subsidiary_of | O1: series | P1: sales_price | Q1: manager | R1: regional_office
A2: 1C1I7A6R | B2: Moses Frase | C2: GTX Plus Basic | D2: Cancity | E2: Won | F2: 42663 | G2: 42795 | H2: 1054 | I2: =VLOOKUP(pipeline!D2,account,2,FALSE) -> retail | J2: =VLOOKUP(D2,account,3,FALSE) -> 2001 | K2: =VLOOKUP(D2,account,4,FALSE) -> 718.62 | L2: =VLOOKUP(D2,account,5,FALSE) -> 2448 | M2: =VLOOKUP(D2,account,6,FALSE) -> United States | N2: =VLOOKUP(D2,accounts,7,FALSE) -> 0 | O2: =VLOOKUP(C2,products,2,FALSE) -> GTX | P2: =VLOOKUP(C2,products,3,FALSE) -> 1096 | Q2: =VLOOKUP(B2,sales,2,FALSE) -> Dustin Brinkmann | R2: =VLOOKUP(B2,sales,3,FALSE) -> Central
A3: EC4QE1BX | B3: Darcel Schlecht | C3: MG Special | D3: Cancity | E3: Won | F3: 42668 | G3: 42801 | H3: 50 | I3: =VLOOKUP(pipeline!D3,account,2,FALSE) -> retail | J3: =VLOOKUP(D3,account,3,FALSE) -> 2001 | K3: =VLOOKUP(D3,account,4,FALSE) -> 718.62 | L3: =VLOOKUP(D3,account,5,FALSE) -> 2448 | M3: =VLOOKUP(D3,account,6,FALSE) -> United States | N3: =VLOOKUP(D3,accounts,7,FALSE) -> 0 | O3: =VLOOKUP(C3,products,2,FALSE) -> MG | P3: =VLOOKUP(C3,products,3,FALSE) -> 55 | Q3: =VLOOKUP(B3,sales,2,FALSE) -> Melvin Marxen | R3: =VLOOKUP(B3,sales,3,FALSE) -> Central
A4: MV1LWRNH | B4: Moses Frase | C4: GTX Basic | D4: Codehow | E4: Won | F4: 42668 | G4: 42803 | H4: 588 | I4: =VLOOKUP(pipeline!D4,account,2,FALSE) -> software | J4: =VLOOKUP(D4,account,3,FALSE) -> 1998 | K4: =VLOOKUP(D4,account,4,FALSE) -> 2714.9 | L4: =VLOOKUP(D4,account,5,FALSE) -> 2641 | M4: =VLOOKUP(D4,account,6,FALSE) -> United States | N4: =VLOOKUP(D4,accounts,7,FALSE) -> Acme Corporation | O4: =VLOOKUP(C4,products,2,FALSE) -> GTX | P4: =VLOOKUP(C4,products,3,FALSE) -> 550 | Q4: =VLOOKUP(B4,sales,2,FALSE) -> Dustin Brinkmann | R4: =VLOOKUP(B4,sales,3,FALSE) -> Central
A5: PE84CX4O | B5: Zane Levy | C5: GTX Basic | D5: Hatfan | E5: Won | F5: 42668 | G5: 42796 | H5: 517 | I5: =VLOOKUP(pipeline!D5,account,2,FALSE) -> services | J5: =VLOOKUP(D5,account,3,FALSE) -> 1982 | K5: =VLOOKUP(D5,account,4,FALSE) -> 792.46 | L5: =VLOOKUP(D5,account,5,FALSE) -> 1299 | M5: =VLOOKUP(D5,account,6,FALSE) -> United States | N5: =VLOOKUP(D5,accounts,7,FALSE) -> 0 | O5: =VLOOKUP(C5,products,2,FALSE) -> GTX | P5: =VLOOKUP(C5,products,3,FALSE) -> 550 | Q5: =VLOOKUP(B5,sales,2,FALSE) -> Summer Sewald | R5: =VLOOKUP(B5,sales,3,FALSE) -> West
A6: ZNBS69V1 | B6: Anna Snelling | C6: MG Special | D6: Ron-tech | E6: Won | F6: 42672 | G6: 42795 | H6: 49 | I6: =VLOOKUP(pipeline!D6,account,2,FALSE) -> medical | J6: =VLOOKUP(D6,account,3,FALSE) -> 1992 | K6: =VLOOKUP(D6,account,4,FALSE) -> 3922.42 | L6: =VLOOKUP(D6,account,5,FALSE) -> 6837 | M6: =VLOOKUP(D6,account,6,FALSE) -> United States | N6: =VLOOKUP(D6,accounts,7,FALSE) -> 0 | O6: =VLOOKUP(C6,products,2,FALSE) -> MG | P6: =VLOOKUP(C6,products,3,FALSE) -> 55 | Q6: =VLOOKUP(B6,sales,2,FALSE) -> Dustin Brinkmann | R6: =VLOOKUP(B6,sales,3,FALSE) -> Central
A7: 9ME3374G | B7: Vicki Laflamme | C7: MG Special | D7: J-Texon | E7: Won | F7: 42673 | G7: 42796 | H7: 57 | I7: =VLOOKUP(pipeline!D7,account,2,FALSE) -> retail | J7: =VLOOKUP(D7,account,3,FALSE) -> 1989 | K7: =VLOOKUP(D7,account,4,FALSE) -> 1388.67 | L7: =VLOOKUP(D7,account,5,FALSE) -> 3583 | M7: =VLOOKUP(D7,account,6,FALSE) -> United States | N7: =VLOOKUP(D7,accounts,7,FALSE) -> 0 | O7: =VLOOKUP(C7,products,2,FALSE) -> MG | P7: =VLOOKUP(C7,products,3,FALSE) -> 55 | Q7: =VLOOKUP(B7,sales,2,FALSE) -> Celia Rouche | R7: =VLOOKUP(B7,sales,3,FALSE) -> West
A8: 7GN8Q4LL | B8: Markita Hansen | C8: GTX Basic | D8: Cheers | E8: Won | F8: 42675 | G8: 42801 | H8: 601 | I8: =VLOOKUP(pipeline!D8,account,2,FALSE) -> entertainment | J8: =VLOOKUP(D8,account,3,FALSE) -> 1993 | K8: =VLOOKUP(D8,account,4,FALSE) -> 4269.9 | L8: =VLOOKUP(D8,account,5,FALSE) -> 6472 | M8: =VLOOKUP(D8,account,6,FALSE) -> United States | N8: =VLOOKUP(D8,accounts,7,FALSE) -> Massive Dynamic | O8: =VLOOKUP(C8,products,2,FALSE) -> GTX | P8: =VLOOKUP(C8,products,3,FALSE) -> 550 | Q8: =VLOOKUP(B8,sales,2,FALSE) -> Celia Rouche | R8: =VLOOKUP(B8,sales,3,FALSE) -> West
A9: OLK9LKZB | B9: Niesha Huffines | C9: GTX Plus Basic | D9: Zumgoity | E9: Won | F9: 42675 | G9: 42797 | H9: 1026 | I9: =VLOOKUP(pipeline!D9,account,2,FALSE) -> medical | J9: =VLOOKUP(D9,account,3,FALSE) -> 1984 | K9: =VLOOKUP(D9,account,4,FALSE) -> 441.08 | L9: =VLOOKUP(D9,account,5,FALSE) -> 1210 | M9: =VLOOKUP(D9,account,6,FALSE) -> United States | N9: =VLOOKUP(D9,accounts,7,FALSE) -> 0 | O9: =VLOOKUP(C9,products,2,FALSE) -> GTX | P9: =VLOOKUP(C9,products,3,FALSE) -> 1096 | Q9: =VLOOKUP(B9,sales,2,FALSE) -> Melvin Marxen | R9: =VLOOKUP(B9,sales,3,FALSE) -> Central
A10: NL3JZH1Z | B10: Anna Snelling | C10: MG Special | D10: Bioholding | E10: Won | F10: 42678 | G10: 42804 | H10: 53 | I10: =VLOOKUP(pipeline!D10,account,2,FALSE) -> medical | J10: =VLOOKUP(D10,account,3,FALSE) -> 2012 | K10: =VLOOKUP(D10,account,4,FALSE) -> 587.34 | L10: =VLOOKUP(D10,account,5,FALSE) -> 1356 | M10: =VLOOKUP(D10,account,6,FALSE) -> Philipines | N10: =VLOOKUP(D10,accounts,7,FALSE) -> 0 | O10: =VLOOKUP(C10,products,2,FALSE) -> MG | P10: =VLOOKUP(C10,products,3,FALSE) -> 55 | Q10: =VLOOKUP(B10,sales,2,FALSE) -> Dustin Brinkmann | R10: =VLOOKUP(B10,sales,3,FALSE) -> Central
A11: S8DX3XOU | B11: James Ascencio | C11: GTX Plus Pro | D11: Sunnamplex | E11: Won | F11: 42678 | G11: 42804 | H11: 5169 | I11: =VLOOKUP(pipeline!D11,account,2,FALSE) -> marketing | J11: =VLOOKUP(D11,account,3,FALSE) -> 2008 | K11: =VLOOKUP(D11,account,4,FALSE) -> 894.37 | L11: =VLOOKUP(D11,account,5,FALSE) -> 1593 | M11: =VLOOKUP(D11,account,6,FALSE) -> Poland | N11: =VLOOKUP(D11,accounts,7,FALSE) -> 0 | O11: =VLOOKUP(C11,products,2,FALSE) -> GTX | P11: =VLOOKUP(C11,products,3,FALSE) -> 5482 | Q11: =VLOOKUP(B11,sales,2,FALSE) -> Summer Sewald | R11: =VLOOKUP(B11,sales,3,FALSE) -> West
A12: ENB2XD8G | B12: Maureen Marcano | C12: GTX Plus Pro | D12: Sonron | E12: Won | F12: 42678 | G12: 42800 | H12: 4631 | I12: =VLOOKUP(pipeline!D12,account,2,FALSE) -> telecommunications | J12: =VLOOKUP(D12,account,3,FALSE) -> 1999 | K12: =VLOOKUP(D12,account,4,FALSE) -> 1699.85 | L12: =VLOOKUP(D12,account,5,FALSE) -> 5108 | M12: =VLOOKUP(D12,account,6,FALSE) -> United States | N12: =VLOOKUP(D12,accounts,7,FALSE) -> 0 | O12: =VLOOKUP(C12,products,2,FALSE) -> GTX | P12: =VLOOKUP(C12,products,3,FALSE) -> 5482 | Q12: =VLOOKUP(B12,sales,2,FALSE) -> Summer Sewald | R12: =VLOOKUP(B12,sales,3,FALSE) -> West
A13: 09YE9QOV | B13: Hayden Neloms | C13: MG Advanced | D13: Finjob | E13: Won | F13: 42679 | G13: 42805 | H13: 3393 | I13: =VLOOKUP(pipeline!D13,account,2,FALSE) -> employment | J13: =VLOOKUP(D13,account,3,FALSE) -> 1988 | K13: =VLOOKUP(D13,account,4,FALSE) -> 2059.9 | L13: =VLOOKUP(D13,account,5,FALSE) -> 3644 | M13: =VLOOKUP(D13,account,6,FALSE) -> United States | N13: =VLOOKUP(D13,accounts,7,FALSE) -> 0 | O13: =VLOOKUP(C13,products,2,FALSE) -> MG | P13: =VLOOKUP(C13,products,3,FALSE) -> 3393 | Q13: =VLOOKUP(B13,sales,2,FALSE) -> Celia Rouche | R13: =VLOOKUP(B13,sales,3,FALSE) -> West
... A22: SBCR987L | B22: Kami Bicknell | C22: GTX Basic | D22: Zoomit | E22: Won | F22: 42684 | G22: 42817 | H22: 590 | I22: =VLOOKUP(pipeline!D22,account,2,FALSE) -> entertainment | J22: =VLOOKUP(D22,account,3,FALSE) -> 1992 | K22: =VLOOKUP(D22,account,4,FALSE) -> 324.19 | L22: =VLOOKUP(D22,account,5,FALSE) -> 978 | M22: =VLOOKUP(D22,account,6,FALSE) -> United States | N22: =VLOOKUP(D22,accounts,7,FALSE) -> 0 | O22: =VLOOKUP(C22,products,2,FALSE) -> GTX | P22: =VLOOKUP(C22,products,3,FALSE) -> 550 | Q22: =VLOOKUP(B22,sales,2,FALSE) -> Summer Sewald | R22: =VLOOKUP(B22,sales,3,FALSE) -> West
A23: UP409DSB | B23: Maureen Marcano | C23: MG Advanced | D23: Ganjaflex | E23: Engaging | F23: 42684 | I23: =VLOOKUP(pipeline!D23,account,2,FALSE) -> retail | J23: =VLOOKUP(D23,account,3,FALSE) -> 1995 | K23: =VLOOKUP(D23,account,4,FALSE) -> 5158.71 | L23: =VLOOKUP(D23,account,5,FALSE) -> 17479 | M23: =VLOOKUP(D23,account,6,FALSE) -> Japan | N23: =VLOOKUP(D23,accounts,7,FALSE) -> 0 | O23: =VLOOKUP(C23,products,2,FALSE) -> MG | P23: =VLOOKUP(C23,products,3,FALSE) -> 3393 | Q23: =VLOOKUP(B23,sales,2,FALSE) -> Summer Sewald | R23: =VLOOKUP(B23,sales,3,FALSE) -> West
A24: JSD4APT2 | B24: Versie Hillebrand | C24: MG Special | D24: Bioholding | E24: Won | F24: 42684 | G24: 42806 | H24: 61 | I24: =VLOOKUP(pipeline!D24,account,2,FALSE) -> medical | J24: =VLOOKUP(D24,account,3,FALSE) -> 2012 | K24: =VLOOKUP(D24,account,4,FALSE) -> 587.34 | L24: =VLOOKUP(D24,account,5,FALSE) -> 1356 | M24: =VLOOKUP(D24,account,6,FALSE) -> Philipines | N24: =VLOOKUP(D24,accounts,7,FALSE) -> 0 | O24: =VLOOKUP(C24,products,2,FALSE) -> MG | P24: =VLOOKUP(C24,products,3,FALSE) -> 55 | Q24: =VLOOKUP(B24,sales,2,FALSE) -> Dustin Brinkmann | R24: =VLOOKUP(B24,sales,3,FALSE) -> Central
A25: AO9Z2D17 | B25: Violet Mclelland | C25: GTX Plus Pro | D25: Xx-zobam | E25: Lost | F25: 42684 | G25: 42805 | H25: 0 | I25: =VLOOKUP(pipeline!D25,account,2,FALSE) -> entertainment | J25: =VLOOKUP(D25,account,3,FALSE) -> 1989 | K25: =VLOOKUP(D25,account,4,FALSE) -> 3838.39 | L25: =VLOOKUP(D25,account,5,FALSE) -> 8274 | M25: =VLOOKUP(D25,account,6,FALSE) -> United States | N25: =VLOOKUP(D25,accounts,7,FALSE) -> 0 | O25: =VLOOKUP(C25,products,2,FALSE) -> GTX | P25: =VLOOKUP(C25,products,3,FALSE) -> 5482 | Q25: =VLOOKUP(B25,sales,2,FALSE) -> Cara Losch | R25: =VLOOKUP(B25,sales,3,FALSE) -> East
A26: 5M58DTJK | B26: Elease Gluck | C26: MG Special | D26: Cheers | E26: Won | F26: 42685 | G26: 42799 | H26: 58 | I26: =VLOOKUP(pipeline!D26,account,2,FALSE) -> entertainment | J26: =VLOOKUP(D26,account,3,FALSE) -> 1993 | K26: =VLOOKUP(D26,account,4,FALSE) -> 4269.9 | L26: =VLOOKUP(D26,account,5,FALSE) -> 6472 | M26: =VLOOKUP(D26,account,6,FALSE) -> United States | N26: =VLOOKUP(D26,accounts,7,FALSE) -> Massive Dynamic | O26: =VLOOKUP(C26,products,2,FALSE) -> MG | P26: =VLOOKUP(C26,products,3,FALSE) -> 55 | Q26: =VLOOKUP(B26,sales,2,FALSE) -> Celia Rouche | R26: =VLOOKUP(B26,sales,3,FALSE) -> West
A27: EAZDUUM9 | B27: Rosie Papadopoulos | C27: MG Advanced | D27: Zotware | E27: Lost | F27: 42685 | G27: 42795 | H27: 0 | I27: =VLOOKUP(pipeline!D27,account,2,FALSE) -> software | J27: =VLOOKUP(D27,account,3,FALSE) -> 1979 | K27: =VLOOKUP(D27,account,4,FALSE) -> 4478.47 | L27: =VLOOKUP(D27,account,5,FALSE) -> 13809 | M27: =VLOOKUP(D27,account,6,FALSE) -> United States | N27: =VLOOKUP(D27,accounts,7,FALSE) -> 0 | O27: =VLOOKUP(C27,products,2,FALSE) -> MG | P27: =VLOOKUP(C27,products,3,FALSE) -> 3393 | Q27: =VLOOKUP(B27,sales,2,FALSE) -> Cara Losch | R27: =VLOOKUP(B27,sales,3,FALSE) -> East
A28: 2STUSOFE | B28: Versie Hillebrand | C28: MG Special | D28: dambase | E28: Won | F28: 42685 | G28: 42797 | H28: 67 | I28: =VLOOKUP(pipeline!D28,account,2,FALSE) -> marketing | J28: =VLOOKUP(D28,account,3,FALSE) -> 1995 | K28: =VLOOKUP(D28,account,4,FALSE) -> 2173.98 | L28: =VLOOKUP(D28,account,5,FALSE) -> 2928 | M28: =VLOOKUP(D28,account,6,FALSE) -> United States | N28: =VLOOKUP(D28,accounts,7,FALSE) -> Inity | O28: =VLOOKUP(C28,products,2,FALSE) -> MG | P28: =VLOOKUP(C28,products,3,FALSE) -> 55 | Q28: =VLOOKUP(B28,sales,2,FALSE) -> Dustin Brinkmann | R28: =VLOOKUP(B28,sales,3,FALSE) -> Central
A29: KU28360J | B29: Kary Hendrixson | C29: GTX Basic | D29: Fasehatice | E29: Won | F29: 42686 | G29: 42813 | H29: 578 | I29: =VLOOKUP(pipeline!D29,account,2,FALSE) -> retail | J29: =VLOOKUP(D29,account,3,FALSE) -> 1990 | K29: =VLOOKUP(D29,account,4,FALSE) -> 4968.91 | L29: =VLOOKUP(D29,account,5,FALSE) -> 7523 | M29: =VLOOKUP(D29,account,6,FALSE) -> United States | N29: =VLOOKUP(D29,accounts,7,FALSE) -> 0 | O29: =VLOOKUP(C29,products,2,FALSE) -> GTX | P29: =VLOOKUP(C29,products,3,FALSE) -> 550 | Q29: =VLOOKUP(B29,sales,2,FALSE) -> Summer Sewald | R29: =VLOOKUP(B29,sales,3,FALSE) -> West
A30: N4SD17JR | B30: Reed Clapper | C30: GTX Basic | D30: Acme Corporation | E30: Won | F30: 42686 | G30: 42795 | H30: 556 | I30: =VLOOKUP(pipeline!D30,account,2,FALSE) -> technolgy | J30: =VLOOKUP(D30,account,3,FALSE) -> 1996 | K30: =VLOOKUP(D30,account,4,FALSE) -> 1100.04 | L30: =VLOOKUP(D30,account,5,FALSE) -> 2822 | M30: =VLOOKUP(D30,account,6,FALSE) -> United States | N30: =VLOOKUP(D30,accounts,7,FALSE) -> 0 | O30: =VLOOKUP(C30,products,2,FALSE) -> GTX | P30: =VLOOKUP(C30,products,3,FALSE) -> 550 | Q30: =VLOOKUP(B30,sales,2,FALSE) -> Rocco Neubert | R30: =VLOOKUP(B30,sales,3,FALSE) -> East
A31: E67P9Y3Q | B31: Rosalina Dieter | C31: GTX Basic | D31: Green-Plus | E31: Won | F31: 42686 | G31: 42797 | H31: 635 | I31: =VLOOKUP(pipeline!D31,account,2,FALSE) -> services | J31: =VLOOKUP(D31,account,3,FALSE) -> 2003 | K31: =VLOOKUP(D31,account,4,FALSE) -> 692.19 | L31: =VLOOKUP(D31,account,5,FALSE) -> 1922 | M31: =VLOOKUP(D31,account,6,FALSE) -> United States | N31: =VLOOKUP(D31,accounts,7,FALSE) -> 0 | O31: =VLOOKUP(C31,products,2,FALSE) -> GTX | P31: =VLOOKUP(C31,products,3,FALSE) -> 550 | Q31: =VLOOKUP(B31,sales,2,FALSE) -> Celia Rouche | R31: =VLOOKUP(B31,sales,3,FALSE) -> West
A32: AT3MMVIS | B32: Wilburn Farren | C32: MG Advanced | D32: The New York Inquirer | E32: Won | F32: 42686 | G32: 42801 | H32: 3045 | I32: =VLOOKUP(pipeline!D32,account,2,FALSE) -> medical | J32: =VLOOKUP(D32,account,3,FALSE) -> 1996 | K32: =VLOOKUP(D32,account,4,FALSE) -> 439.21 | L32: =VLOOKUP(D32,account,5,FALSE) -> 792 | M32: =VLOOKUP(D32,account,6,FALSE) -> United States | N32: =VLOOKUP(D32,accounts,7,FALSE) -> 0 | O32: =VLOOKUP(C32,products,2,FALSE) -> MG | P32: =VLOOKUP(C32,products,3,FALSE) -> 3393 | Q32: =VLOOKUP(B32,sales,2,FALSE) -> Cara Losch | R32: =VLOOKUP(B32,sales,3,FALSE) -> East
A33: REJ11LRY | B33: Garret Kinder | C33: GTX Plus Basic | D33: Mathtouch | E33: Won | F33: 42687 | G33: 42808 | H33: 1233 | I33: =VLOOKUP(pipeline!D33,account,2,FALSE) -> marketing | J33: =VLOOKUP(D33,account,3,FALSE) -> 1984 | K33: =VLOOKUP(D33,account,4,FALSE) -> 3027.46 | L33: =VLOOKUP(D33,account,5,FALSE) -> 9516 | M33: =VLOOKUP(D33,account,6,FALSE) -> Jordan | N33: =VLOOKUP(D33,accounts,7,FALSE) -> 0 | O33: =VLOOKUP(C33,products,2,FALSE) -> GTX | P33: =VLOOKUP(C33,products,3,FALSE) -> 1096 | Q33: =VLOOKUP(B33,sales,2,FALSE) -> Cara Losch | R33: =VLOOKUP(B33,sales,3,FALSE) -> East
A34: ERV0CAZ7 | B34: Versie Hillebrand | C34: MG Special | D34: Zumgoity | E34: Won | F34: 42687 | G34: 42803 | H34: 60 | I34: =VLOOKUP(pipeline!D34,account,2,FALSE) -> medical | J34: =VLOOKUP(D34,account,3,FALSE) -> 1984 | K34: =VLOOKUP(D34,account,4,FALSE) -> 441.08 | L34: =VLOOKUP(D34,account,5,FALSE) -> 1210 | M34: =VLOOKUP(D34,account,6,FALSE) -> United States | N34: =VLOOKUP(D34,accounts,7,FALSE) -> 0 | O34: =VLOOKUP(C34,products,2,FALSE) -> MG | P34: =VLOOKUP(C34,products,3,FALSE) -> 55 | Q34: =VLOOKUP(B34,sales,2,FALSE) -> Dustin Brinkmann | R34: =VLOOKUP(B34,sales,3,FALSE) -> Central
A35: 8SOQADK7 | B35: Anna Snelling | C35: MG Special | D35: Gogozoom | E35: Lost | F35: 42688 | G35: 42824 | H35: 0 | I35: =VLOOKUP(pipeline!D35,account,2,FALSE) -> telecommunications | J35: =VLOOKUP(D35,account,3,FALSE) -> 2007 | K35: =VLOOKUP(D35,account,4,FALSE) -> 86.68 | L35: =VLOOKUP(D35,account,5,FALSE) -> 187 | M35: =VLOOKUP(D35,account,6,FALSE) -> United States | N35: =VLOOKUP(D35,accounts,7,FALSE) -> Sonron | O35: =VLOOKUP(C35,products,2,FALSE) -> MG | P35: =VLOOKUP(C35,products,3,FALSE) -> 55 | Q35: =VLOOKUP(B35,sales,2,FALSE) -> Dustin Brinkmann | R35: =VLOOKUP(B35,sales,3,FALSE) -> Central
... A53: MYDUMR3R | B53: Lajuana Vencill | C53: GTX Basic | D53: Rangreen | E53: Won | F53: 42694 | G53: 42798 | H53: 559 | I53: =VLOOKUP(pipeline!D53,account,2,FALSE) -> technolgy | J53: =VLOOKUP(D53,account,3,FALSE) -> 1987 | K53: =VLOOKUP(D53,account,4,FALSE) -> 2938.67 | L53: =VLOOKUP(D53,account,5,FALSE) -> 8775 | M53: =VLOOKUP(D53,account,6,FALSE) -> Panama | N53: =VLOOKUP(D53,accounts,7,FALSE) -> 0 | O53: =VLOOKUP(C53,products,2,FALSE) -> GTX | P53: =VLOOKUP(C53,products,3,FALSE) -> 550 | Q53: =VLOOKUP(B53,sales,2,FALSE) -> Dustin Brinkmann | R53: =VLOOKUP(B53,sales,3,FALSE) -> Central
A54: 0DRC1U9Q | B54: Maureen Marcano | C54: GTX Basic | D54: Green-Plus | E54: Engaging | F54: 42694 | I54: =VLOOKUP(pipeline!D54,account,2,FALSE) -> services | J54: =VLOOKUP(D54,account,3,FALSE) -> 2003 | K54: =VLOOKUP(D54,account,4,FALSE) -> 692.19 | L54: =VLOOKUP(D54,account,5,FALSE) -> 1922 | M54: =VLOOKUP(D54,account,6,FALSE) -> United States | N54: =VLOOKUP(D54,accounts,7,FALSE) -> 0 | O54: =VLOOKUP(C54,products,2,FALSE) -> GTX | P54: =VLOOKUP(C54,products,3,FALSE) -> 550 | Q54: =VLOOKUP(B54,sales,2,FALSE) -> Summer Sewald | R54: =VLOOKUP(B54,sales,3,FALSE) -> West
A55: 37JFKD4I | B55: Niesha Huffines | C55: GTX Plus Basic | D55: dambase | E55: Won | F55: 42694 | G55: 42803 | H55: 1033 | I55: =VLOOKUP(pipeline!D55,account,2,FALSE) -> marketing | J55: =VLOOKUP(D55,account,3,FALSE) -> 1995 | K55: =VLOOKUP(D55,account,4,FALSE) -> 2173.98 | L55: =VLOOKUP(D55,account,5,FALSE) -> 2928 | M55: =VLOOKUP(D55,account,6,FALSE) -> United States | N55: =VLOOKUP(D55,accounts,7,FALSE) -> Inity | O55: =VLOOKUP(C55,products,2,FALSE) -> GTX | P55: =VLOOKUP(C55,products,3,FALSE) -> 1096 | Q55: =VLOOKUP(B55,sales,2,FALSE) -> Melvin Marxen | R55: =VLOOKUP(B55,sales,3,FALSE) -> Central
A56: 25YKPHX8 | B56: Donn Cantrell | C56: GTX Basic | D56: Kan-code | E56: Won | F56: 42695 | G56: 42815 | H56: 462 | I56: =VLOOKUP(pipeline!D56,account,2,FALSE) -> software | J56: =VLOOKUP(D56,account,3,FALSE) -> 1982 | K56: =VLOOKUP(D56,account,4,FALSE) -> 11698.03 | L56: =VLOOKUP(D56,account,5,FALSE) -> 34288 | M56: =VLOOKUP(D56,account,6,FALSE) -> United States | N56: =VLOOKUP(D56,accounts,7,FALSE) -> 0 | O56: =VLOOKUP(C56,products,2,FALSE) -> GTX | P56: =VLOOKUP(C56,products,3,FALSE) -> 550 | Q56: =VLOOKUP(B56,sales,2,FALSE) -> Rocco Neubert | R56: =VLOOKUP(B56,sales,3,FALSE) -> East
A57: BXXMA7F3 | B57: Hayden Neloms | C57: MG Advanced | D57: Nam-zim | E57: Lost | F57: 42695 | G57: 42795 | H57: 0 | I57: =VLOOKUP(pipeline!D57,account,2,FALSE) -> services | J57: =VLOOKUP(D57,account,3,FALSE) -> 1987 | K57: =VLOOKUP(D57,account,4,FALSE) -> 405.59 | L57: =VLOOKUP(D57,account,5,FALSE) -> 1179 | M57: =VLOOKUP(D57,account,6,FALSE) -> Brazil | N57: =VLOOKUP(D57,accounts,7,FALSE) -> Warephase | O57: =VLOOKUP(C57,products,2,FALSE) -> MG | P57: =VLOOKUP(C57,products,3,FALSE) -> 3393 | Q57: =VLOOKUP(B57,sales,2,FALSE) -> Celia Rouche | R57: =VLOOKUP(B57,sales,3,FALSE) -> West
A58: MFX2LR1Q | B58: Lajuana Vencill | C58: MG Advanced | D58: Ron-tech | E58: Won | F58: 42695 | G58: 42809 | H58: 3573 | I58: =VLOOKUP(pipeline!D58,account,2,FALSE) -> medical | J58: =VLOOKUP(D58,account,3,FALSE) -> 1992 | K58: =VLOOKUP(D58,account,4,FALSE) -> 3922.42 | L58: =VLOOKUP(D58,account,5,FALSE) -> 6837 | M58: =VLOOKUP(D58,account,6,FALSE) -> United States | N58: =VLOOKUP(D58,accounts,7,FALSE) -> 0 | O58: =VLOOKUP(C58,products,2,FALSE) -> MG | P58: =VLOOKUP(C58,products,3,FALSE) -> 3393 | Q58: =VLOOKUP(B58,sales,2,FALSE) -> Dustin Brinkmann | R58: =VLOOKUP(B58,sales,3,FALSE) -> Central
A59: 96BSG7R1 | B59: Zane Levy | C59: GTX Plus Basic | D59: Sunnamplex | E59: Lost | F59: 42695 | G59: 42811 | H59: 0 | I59: =VLOOKUP(pipeline!D59,account,2,FALSE) -> marketing | J59: =VLOOKUP(D59,account,3,FALSE) -> 2008 | K59: =VLOOKUP(D59,account,4,FALSE) -> 894.37 | L59: =VLOOKUP(D59,account,5,FALSE) -> 1593 | M59: =VLOOKUP(D59,account,6,FALSE) -> Poland | N59: =VLOOKUP(D59,accounts,7,FALSE) -> 0 | O59: =VLOOKUP(C59,products,2,FALSE) -> GTX | P59: =VLOOKUP(C59,products,3,FALSE) -> 1096 | Q59: =VLOOKUP(B59,sales,2,FALSE) -> Summer Sewald | R59: =VLOOKUP(B59,sales,3,FALSE) -> West
A60: 7FQMSWIX | B60: Corliss Cosme | C60: MG Special | D60: Bioplex | E60: Won | F60: 42696 | G60: 42798 | H60: 62 | I60: =VLOOKUP(pipeline!D60,account,2,FALSE) -> medical | J60: =VLOOKUP(D60,account,3,FALSE) -> 1991 | K60: =VLOOKUP(D60,account,4,FALSE) -> 326.82 | L60: =VLOOKUP(D60,account,5,FALSE) -> 1016 | M60: =VLOOKUP(D60,account,6,FALSE) -> United States | N60: =VLOOKUP(D60,accounts,7,FALSE) -> 0 | O60: =VLOOKUP(C60,products,2,FALSE) -> MG | P60: =VLOOKUP(C60,products,3,FALSE) -> 55 | Q60: =VLOOKUP(B60,sales,2,FALSE) -> Cara Losch | R60: =VLOOKUP(B60,sales,3,FALSE) -> East
A61: GS1QVWCR | B61: Kami Bicknell | C61: GTX Basic | D61: Plusstrip | E61: Won | F61: 42696 | G61: 42825 | H61: 566 | I61: =VLOOKUP(pipeline!D61,account,2,FALSE) -> entertainment | J61: =VLOOKUP(D61,account,3,FALSE) -> 2002 | K61: =VLOOKUP(D61,account,4,FALSE) -> 349.81 | L61: =VLOOKUP(D61,account,5,FALSE) -> 315 | M61: =VLOOKUP(D61,account,6,FALSE) -> United States | N61: =VLOOKUP(D61,accounts,7,FALSE) -> 0 | O61: =VLOOKUP(C61,products,2,FALSE) -> GTX | P61: =VLOOKUP(C61,products,3,FALSE) -> 550 | Q61: =VLOOKUP(B61,sales,2,FALSE) -> Summer Sewald | R61: =VLOOKUP(B61,sales,3,FALSE) -> West
A62: ZWH8FXY3 | B62: Marty Freudenburg | C62: GTX Basic | D62: Toughzap | E62: Won | F62: 42696 | G62: 42797 | H62: 508 | I62: =VLOOKUP(pipeline!D62,account,2,FALSE) -> retail | J62: =VLOOKUP(D62,account,3,FALSE) -> 1995 | K62: =VLOOKUP(D62,account,4,FALSE) -> 332.43 | L62: =VLOOKUP(D62,account,5,FALSE) -> 799 | M62: =VLOOKUP(D62,account,6,FALSE) -> United States | N62: =VLOOKUP(D62,accounts,7,FALSE) -> 0 | O62: =VLOOKUP(C62,products,2,FALSE) -> GTX | P62: =VLOOKUP(C62,products,3,FALSE) -> 550 | Q62: =VLOOKUP(B62,sales,2,FALSE) -> Melvin Marxen | R62: =VLOOKUP(B62,sales,3,FALSE) -> Central
A63: 2U94Y3Q9 | B63: Rosie Papadopoulos | C63: MG Advanced | D63: Vehement Capital Partners | E63: Lost | F63: 42696 | G63: 42814 | H63: 0 | I63: =VLOOKUP(pipeline!D63,account,2,FALSE) -> finance | J63: =VLOOKUP(D63,account,3,FALSE) -> 1993 | K63: =VLOOKUP(D63,account,4,FALSE) -> 646.1 | L63: =VLOOKUP(D63,account,5,FALSE) -> 883 | M63: =VLOOKUP(D63,account,6,FALSE) -> United States | N63: =VLOOKUP(D63,accounts,7,FALSE) -> Golddex | O63: =VLOOKUP(C63,products,2,FALSE) -> MG | P63: =VLOOKUP(C63,products,3,FALSE) -> 3393 | Q63: =VLOOKUP(B63,sales,2,FALSE) -> Cara Losch | R63: =VLOOKUP(B63,sales,3,FALSE) -> East
A64: AAR79NOO | B64: Versie Hillebrand | C64: MG Special | D64: Codehow | E64: Won | F64: 42696 | G64: 42805 | H64: 51 | I64: =VLOOKUP(pipeline!D64,account,2,FALSE) -> software | J64: =VLOOKUP(D64,account,3,FALSE) -> 1998 | K64: =VLOOKUP(D64,account,4,FALSE) -> 2714.9 | L64: =VLOOKUP(D64,account,5,FALSE) -> 2641 | M64: =VLOOKUP(D64,account,6,FALSE) -> United States | N64: =VLOOKUP(D64,accounts,7,FALSE) -> Acme Corporation | O64: =VLOOKUP(C64,products,2,FALSE) -> MG | P64: =VLOOKUP(C64,products,3,FALSE) -> 55 | Q64: =VLOOKUP(B64,sales,2,FALSE) -> Dustin Brinkmann | R64: =VLOOKUP(B64,sales,3,FALSE) -> Central
A65: M7I5O9YU | B65: Corliss Cosme | C65: GTX Basic | D65: Cheers | E65: Engaging | F65: 42697 | I65: =VLOOKUP(pipeline!D65,account,2,FALSE) -> entertainment | J65: =VLOOKUP(D65,account,3,FALSE) -> 1993 | K65: =VLOOKUP(D65,account,4,FALSE) -> 4269.9 | L65: =VLOOKUP(D65,account,5,FALSE) -> 6472 | M65: =VLOOKUP(D65,account,6,FALSE) -> United States | N65: =VLOOKUP(D65,accounts,7,FALSE) -> Massive Dynamic | O65: =VLOOKUP(C65,products,2,FALSE) -> GTX | P65: =VLOOKUP(C65,products,3,FALSE) -> 550 | Q65: =VLOOKUP(B65,sales,2,FALSE) -> Cara Losch | R65: =VLOOKUP(B65,sales,3,FALSE) -> East
A66: LXZA2OSZ | B66: Corliss Cosme | C66: GTX Plus Pro | D66: Ontomedia | E66: Won | F66: 42697 | G66: 42797 | H66: 5790 | I66: =VLOOKUP(pipeline!D66,account,2,FALSE) -> employment | J66: =VLOOKUP(D66,account,3,FALSE) -> 1997 | K66: =VLOOKUP(D66,account,4,FALSE) -> 882.12 | L66: =VLOOKUP(D66,account,5,FALSE) -> 2769 | M66: =VLOOKUP(D66,account,6,FALSE) -> United States | N66: =VLOOKUP(D66,accounts,7,FALSE) -> 0 | O66: =VLOOKUP(C66,products,2,FALSE) -> GTX | P66: =VLOOKUP(C66,products,3,FALSE) -> 5482 | Q66: =VLOOKUP(B66,sales,2,FALSE) -> Cara Losch | R66: =VLOOKUP(B66,sales,3,FALSE) -> East
A67: N0ONCYVZ | B67: Donn Cantrell | C67: MG Special | D67: Kinnamplus | E67: Lost | F67: 42697 | G67: 42824 | H67: 0 | I67: =VLOOKUP(pipeline!D67,account,2,FALSE) -> retail | J67: =VLOOKUP(D67,account,3,FALSE) -> 2004 | K67: =VLOOKUP(D67,account,4,FALSE) -> 702.72 | L67: =VLOOKUP(D67,account,5,FALSE) -> 1831 | M67: =VLOOKUP(D67,account,6,FALSE) -> United States | N67: =VLOOKUP(D67,accounts,7,FALSE) -> 0 | O67: =VLOOKUP(C67,products,2,FALSE) -> MG | P67: =VLOOKUP(C67,products,3,FALSE) -> 55 | Q67: =VLOOKUP(B67,sales,2,FALSE) -> Rocco Neubert | R67: =VLOOKUP(B67,sales,3,FALSE) -> East
A68: RU023K5W | B68: Gladys Colclough | C68: MG Advanced | D68: Finhigh | E68: Won | F68: 42697 | G68: 42811 | H68: 2972 | I68: =VLOOKUP(pipeline!D68,account,2,FALSE) -> finance | J68: =VLOOKUP(D68,account,3,FALSE) -> 2006 | K68: =VLOOKUP(D68,account,4,FALSE) -> 1102.43 | L68: =VLOOKUP(D68,account,5,FALSE) -> 1759 | M68: =VLOOKUP(D68,account,6,FALSE) -> United States | N68: =VLOOKUP(D68,accounts,7,FALSE) -> 0 | O68: =VLOOKUP(C68,products,2,FALSE) -> MG | P68: =VLOOKUP(C68,products,3,FALSE) -> 3393 | Q68: =VLOOKUP(B68,sales,2,FALSE) -> Melvin Marxen | R68: =VLOOKUP(B68,sales,3,FALSE) -> Central
A69: VDIU10RV | B69: Markita Hansen | C69: MG Special | D69: Lexiqvolax | E69: Engaging | F69: 42697 | I69: =VLOOKUP(pipeline!D69,account,2,FALSE) -> medical | J69: =VLOOKUP(D69,account,3,FALSE) -> 2004 | K69: =VLOOKUP(D69,account,4,FALSE) -> 1618.89 | L69: =VLOOKUP(D69,account,5,FALSE) -> 3889 | M69: =VLOOKUP(D69,account,6,FALSE) -> United States | N69: =VLOOKUP(D69,accounts,7,FALSE) -> 0 | O69: =VLOOKUP(C69,products,2,FALSE) -> MG | P69: =VLOOKUP(C69,products,3,FALSE) -> 55 | Q69: =VLOOKUP(B69,sales,2,FALSE) -> Celia Rouche | R69: =VLOOKUP(B69,sales,3,FALSE) -> West
A70: BZCBQ514 | B70: Markita Hansen | C70: GTX Basic | D70: Y-corporation | E70: Won | F70: 42697 | G70: 42795 | H70: 523 | I70: =VLOOKUP(pipeline!D70,account,2,FALSE) -> employment | J70: =VLOOKUP(D70,account,3,FALSE) -> 1983 | K70: =VLOOKUP(D70,account,4,FALSE) -> 2871.35 | L70: =VLOOKUP(D70,account,5,FALSE) -> 9561 | M70: =VLOOKUP(D70,account,6,FALSE) -> United States | N70: =VLOOKUP(D70,accounts,7,FALSE) -> 0 | O70: =VLOOKUP(C70,products,2,FALSE) -> GTX | P70: =VLOOKUP(C70,products,3,FALSE) -> 550 | Q70: =VLOOKUP(B70,sales,2,FALSE) -> Celia Rouche | R70: =VLOOKUP(B70,sales,3,FALSE) -> West
A71: HEE6P0QH | B71: Anna Snelling | C71: MG Advanced | D71: Statholdings | E71: Won | F71: 42698 | G71: 42819 | H71: 3647 | I71: =VLOOKUP(pipeline!D71,account,2,FALSE) -> employment | J71: =VLOOKUP(D71,account,3,FALSE) -> 1997 | K71: =VLOOKUP(D71,account,4,FALSE) -> 291.27 | L71: =VLOOKUP(D71,account,5,FALSE) -> 586 | M71: =VLOOKUP(D71,account,6,FALSE) -> United States | N71: =VLOOKUP(D71,accounts,7,FALSE) -> 0 | O71: =VLOOKUP(C71,products,2,FALSE) -> MG | P71: =VLOOKUP(C71,products,3,FALSE) -> 3393 | Q71: =VLOOKUP(B71,sales,2,FALSE) -> Dustin Brinkmann | R71: =VLOOKUP(B71,sales,3,FALSE) -> Central
A72: L8CHRJ2B | B72: Cassey Cress | C72: MG Advanced | D72: Umbrella Corporation | E72: Won | F72: 42698 | G72: 42795 | H72: 4200 | I72: =VLOOKUP(pipeline!D72,account,2,FALSE) -> finance | J72: =VLOOKUP(D72,account,3,FALSE) -> 1998 | K72: =VLOOKUP(D72,account,4,FALSE) -> 2022.14 | L72: =VLOOKUP(D72,account,5,FALSE) -> 5113 | M72: =VLOOKUP(D72,account,6,FALSE) -> United States | N72: =VLOOKUP(D72,accounts,7,FALSE) -> 0 | O72: =VLOOKUP(C72,products,2,FALSE) -> MG | P72: =VLOOKUP(C72,products,3,FALSE) -> 3393 | Q72: =VLOOKUP(B72,sales,2,FALSE) -> Rocco Neubert | R72: =VLOOKUP(B72,sales,3,FALSE) -> East
A73: 579LZ3F9 | B73: Daniell Hammack | C73: GTX Plus Basic | D73: J-Texon | E73: Engaging | F73: 42698 | I73: =VLOOKUP(pipeline!D73,account,2,FALSE) -> retail | J73: =VLOOKUP(D73,account,3,FALSE) -> 1989 | K73: =VLOOKUP(D73,account,4,FALSE) -> 1388.67 | L73: =VLOOKUP(D73,account,5,FALSE) -> 3583 | M73: =VLOOKUP(D73,account,6,FALSE) -> United States | N73: =VLOOKUP(D73,accounts,7,FALSE) -> 0 | O73: =VLOOKUP(C73,products,2,FALSE) -> GTX | P73: =VLOOKUP(C73,products,3,FALSE) -> 1096 | Q73: =VLOOKUP(B73,sales,2,FALSE) -> Rocco Neubert | R73: =VLOOKUP(B73,sales,3,FALSE) -> East
A74: SU8JNMP4 | B74: Kami Bicknell | C74: GTX Plus Basic | D74: Bubba Gump | E74: Engaging | F74: 42698 | I74: =VLOOKUP(pipeline!D74,account,2,FALSE) -> software | J74: =VLOOKUP(D74,account,3,FALSE) -> 2002 | K74: =VLOOKUP(D74,account,4,FALSE) -> 987.39 | L74: =VLOOKUP(D74,account,5,FALSE) -> 2253 | M74: =VLOOKUP(D74,account,6,FALSE) -> United States | N74: =VLOOKUP(D74,accounts,7,FALSE) -> 0 | O74: =VLOOKUP(C74,products,2,FALSE) -> GTX | P74: =VLOOKUP(C74,products,3,FALSE) -> 1096 | Q74: =VLOOKUP(B74,sales,2,FALSE) -> Summer Sewald | R74: =VLOOKUP(B74,sales,3,FALSE) -> West
A75: V2X2KMUR | B75: Kami Bicknell | C75: GTX Plus Basic | D75: Faxquote | E75: Won | F75: 42698 | G75: 42822 | H75: 1059 | I75: =VLOOKUP(pipeline!D75,account,2,FALSE) -> telecommunications | J75: =VLOOKUP(D75,account,3,FALSE) -> 1995 | K75: =VLOOKUP(D75,account,4,FALSE) -> 1825.82 | L75: =VLOOKUP(D75,account,5,FALSE) -> 5595 | M75: =VLOOKUP(D75,account,6,FALSE) -> United States | N75: =VLOOKUP(D75,accounts,7,FALSE) -> Sonron | O75: =VLOOKUP(C75,products,2,FALSE) -> GTX | P75: =VLOOKUP(C75,products,3,FALSE) -> 1096 | Q75: =VLOOKUP(B75,sales,2,FALSE) -> Summer Sewald | R75: =VLOOKUP(B75,sales,3,FALSE) -> West
A76: AJIPJP75 | B76: Marty Freudenburg | C76: GTX Plus Basic | D76: Codehow | E76: Lost | F76: 42698 | G76: 42799 | H76: 0 | I76: =VLOOKUP(pipeline!D76,account,2,FALSE) -> software | J76: =VLOOKUP(D76,account,3,FALSE) -> 1998 | K76: =VLOOKUP(D76,account,4,FALSE) -> 2714.9 | L76: =VLOOKUP(D76,account,5,FALSE) -> 2641 | M76: =VLOOKUP(D76,account,6,FALSE) -> United States | N76: =VLOOKUP(D76,accounts,7,FALSE) -> Acme Corporation | O76: =VLOOKUP(C76,products,2,FALSE) -> GTX | P76: =VLOOKUP(C76,products,3,FALSE) -> 1096 | Q76: =VLOOKUP(B76,sales,2,FALSE) -> Melvin Marxen | R76: =VLOOKUP(B76,sales,3,FALSE) -> Central
A77: NYVA2G6U | B77: Versie Hillebrand | C77: MG Special | D77: Dontechi | E77: Won | F77: 42698 | G77: 42796 | H77: 57 | I77: =VLOOKUP(pipeline!D77,account,2,FALSE) -> software | J77: =VLOOKUP(D77,account,3,FALSE) -> 1982 | K77: =VLOOKUP(D77,account,4,FALSE) -> 4618 | L77: =VLOOKUP(D77,account,5,FALSE) -> 10083 | M77: =VLOOKUP(D77,account,6,FALSE) -> United States | N77: =VLOOKUP(D77,accounts,7,FALSE) -> 0 | O77: =VLOOKUP(C77,products,2,FALSE) -> MG | P77: =VLOOKUP(C77,products,3,FALSE) -> 55 | Q77: =VLOOKUP(B77,sales,2,FALSE) -> Dustin Brinkmann | R77: =VLOOKUP(B77,sales,3,FALSE) -> Central
A78: FF45BXTL | B78: Vicki Laflamme | C78: MG Advanced | D78: Konex | E78: Won | F78: 42698 | G78: 42821 | H78: 3671 | I78: =VLOOKUP(pipeline!D78,account,2,FALSE) -> technolgy | J78: =VLOOKUP(D78,account,3,FALSE) -> 1980 | K78: =VLOOKUP(D78,account,4,FALSE) -> 7708.38 | L78: =VLOOKUP(D78,account,5,FALSE) -> 13756 | M78: =VLOOKUP(D78,account,6,FALSE) -> United States | N78: =VLOOKUP(D78,accounts,7,FALSE) -> 0 | O78: =VLOOKUP(C78,products,2,FALSE) -> MG | P78: =VLOOKUP(C78,products,3,FALSE) -> 3393 | Q78: =VLOOKUP(B78,sales,2,FALSE) -> Celia Rouche | R78: =VLOOKUP(B78,sales,3,FALSE) -> West
A79: TTA9LYBS | B79: Anna Snelling | C79: MG Special | D79: Treequote | E79: Won | F79: 42699 | G79: 42795 | H79: 58 | I79: =VLOOKUP(pipeline!D79,account,2,FALSE) -> telecommunications | J79: =VLOOKUP(D79,account,3,FALSE) -> 1988 | K79: =VLOOKUP(D79,account,4,FALSE) -> 5266.09 | L79: =VLOOKUP(D79,account,5,FALSE) -> 8595 | M79: =VLOOKUP(D79,account,6,FALSE) -> United States | N79: =VLOOKUP(D79,accounts,7,FALSE) -> Sonron | O79: =VLOOKUP(C79,products,2,FALSE) -> MG | P79: =VLOOKUP(C79,products,3,FALSE) -> 55 | Q79: =VLOOKUP(B79,sales,2,FALSE) -> Dustin Brinkmann | R79: =VLOOKUP(B79,sales,3,FALSE) -> Central
A80: PAGZQH8L | B80: Cecily Lampkin | C80: MG Advanced | D80: Treequote | E80: Won | F80: 42699 | G80: 42800 | H80: 3956 | I80: =VLOOKUP(pipeline!D80,account,2,FALSE) -> telecommunications | J80: =VLOOKUP(D80,account,3,FALSE) -> 1988 | K80: =VLOOKUP(D80,account,4,FALSE) -> 5266.09 | L80: =VLOOKUP(D80,account,5,FALSE) -> 8595 | M80: =VLOOKUP(D80,account,6,FALSE) -> United States | N80: =VLOOKUP(D80,accounts,7,FALSE) -> Sonron | O80: =VLOOKUP(C80,products,2,FALSE) -> MG | P80: =VLOOKUP(C80,products,3,FALSE) -> 3393 | Q80: =VLOOKUP(B80,sales,2,FALSE) -> Dustin Brinkmann | R80: =VLOOKUP(B80,sales,3,FALSE) -> Central
A81: J7YF6DS7 | B81: Corliss Cosme | C81: GTX Plus Pro | D81: Betasoloin | E81: Won | F81: 42699 | G81: 42795 | H81: 5964 | I81: =VLOOKUP(pipeline!D81,account,2,FALSE) -> medical | J81: =VLOOKUP(D81,account,3,FALSE) -> 1999 | K81: =VLOOKUP(D81,account,4,FALSE) -> 251.41 | L81: =VLOOKUP(D81,account,5,FALSE) -> 495 | M81: =VLOOKUP(D81,account,6,FALSE) -> United States | N81: =VLOOKUP(D81,accounts,7,FALSE) -> 0 | O81: =VLOOKUP(C81,products,2,FALSE) -> GTX | P81: =VLOOKUP(C81,products,3,FALSE) -> 5482 | Q81: =VLOOKUP(B81,sales,2,FALSE) -> Cara Losch | R81: =VLOOKUP(B81,sales,3,FALSE) -> East
A82: JQBJMETQ | B82: Darcel Schlecht | C82: MG Special | D82: Domzoom | E82: Won | F82: 42699 | G82: 42821 | H82: 49 | I82: =VLOOKUP(pipeline!D82,account,2,FALSE) -> entertainment | J82: =VLOOKUP(D82,account,3,FALSE) -> 1998 | K82: =VLOOKUP(D82,account,4,FALSE) -> 217.87 | L82: =VLOOKUP(D82,account,5,FALSE) -> 551 | M82: =VLOOKUP(D82,account,6,FALSE) -> United States | N82: =VLOOKUP(D82,accounts,7,FALSE) -> 0 | O82: =VLOOKUP(C82,products,2,FALSE) -> MG | P82: =VLOOKUP(C82,products,3,FALSE) -> 55 | Q82: =VLOOKUP(B82,sales,2,FALSE) -> Melvin Marxen | R82: =VLOOKUP(B82,sales,3,FALSE) -> Central
A83: 0LVWSWEW | B83: Violet Mclelland | C83: MG Special | D83: Donquadtech | E83: Won | F83: 42699 | G83: 42800 | H83: 65 | I83: =VLOOKUP(pipeline!D83,account,2,FALSE) -> technolgy | J83: =VLOOKUP(D83,account,3,FALSE) -> 1992 | K83: =VLOOKUP(D83,account,4,FALSE) -> 1712.68 | L83: =VLOOKUP(D83,account,5,FALSE) -> 3194 | M83: =VLOOKUP(D83,account,6,FALSE) -> United States | N83: =VLOOKUP(D83,accounts,7,FALSE) -> Acme Corporation | O83: =VLOOKUP(C83,products,2,FALSE) -> MG | P83: =VLOOKUP(C83,products,3,FALSE) -> 55 | Q83: =VLOOKUP(B83,sales,2,FALSE) -> Cara Losch | R83: =VLOOKUP(B83,sales,3,FALSE) -> East
A84: K53BC1T9 | B84: Anna Snelling | C84: MG Special | D84: Domzoom | E84: Lost | F84: 42700 | G84: 42821 | H84: 0 | I84: =VLOOKUP(pipeline!D84,account,2,FALSE) -> entertainment | J84: =VLOOKUP(D84,account,3,FALSE) -> 1998 | K84: =VLOOKUP(D84,account,4,FALSE) -> 217.87 | L84: =VLOOKUP(D84,account,5,FALSE) -> 551 | M84: =VLOOKUP(D84,account,6,FALSE) -> United States | N84: =VLOOKUP(D84,accounts,7,FALSE) -> 0 | O84: =VLOOKUP(C84,products,2,FALSE) -> MG | P84: =VLOOKUP(C84,products,3,FALSE) -> 55 | Q84: =VLOOKUP(B84,sales,2,FALSE) -> Dustin Brinkmann | R84: =VLOOKUP(B84,sales,3,FALSE) -> Central
A85: 051QTX8Z | B85: Niesha Huffines | C85: GTX Plus Basic | D85: Globex Corporation | E85: Won | F85: 42700 | G85: 42815 | H85: 1080 | I85: =VLOOKUP(pipeline!D85,account,2,FALSE) -> technolgy | J85: =VLOOKUP(D85,account,3,FALSE) -> 2000 | K85: =VLOOKUP(D85,account,4,FALSE) -> 1223.72 | L85: =VLOOKUP(D85,account,5,FALSE) -> 2497 | M85: =VLOOKUP(D85,account,6,FALSE) -> Norway | N85: =VLOOKUP(D85,accounts,7,FALSE) -> 0 | O85: =VLOOKUP(C85,products,2,FALSE) -> GTX | P85: =VLOOKUP(C85,products,3,FALSE) -> 1096 | Q85: =VLOOKUP(B85,sales,2,FALSE) -> Melvin Marxen | R85: =VLOOKUP(B85,sales,3,FALSE) -> Central
A86: 5D2XH04S | B86: Reed Clapper | C86: MG Special | D86: Plussunin | E86: Won | F86: 42700 | G86: 42806 | H86: 57 | I86: =VLOOKUP(pipeline!D86,account,2,FALSE) -> retail | J86: =VLOOKUP(D86,account,3,FALSE) -> 2003 | K86: =VLOOKUP(D86,account,4,FALSE) -> 1419.98 | L86: =VLOOKUP(D86,account,5,FALSE) -> 4018 | M86: =VLOOKUP(D86,account,6,FALSE) -> United States | N86: =VLOOKUP(D86,accounts,7,FALSE) -> 0 | O86: =VLOOKUP(C86,products,2,FALSE) -> MG | P86: =VLOOKUP(C86,products,3,FALSE) -> 55 | Q86: =VLOOKUP(B86,sales,2,FALSE) -> Rocco Neubert | R86: =VLOOKUP(B86,sales,3,FALSE) -> East
... A88: UK0LEZRJ | B88: Kary Hendrixson | C88: GTX Basic | D88: Condax | E88: Won | F88: 42701 | G88: 42797 | H88: 532 | I88: =VLOOKUP(pipeline!D88,account,2,FALSE) -> medical | J88: =VLOOKUP(D88,account,3,FALSE) -> 2017 | K88: =VLOOKUP(D88,account,4,FALSE) -> 4.54 | L88: =VLOOKUP(D88,account,5,FALSE) -> 9 | M88: =VLOOKUP(D88,account,6,FALSE) -> United States | N88: =VLOOKUP(D88,accounts,7,FALSE) -> 0 | O88: =VLOOKUP(C88,products,2,FALSE) -> GTX | P88: =VLOOKUP(C88,products,3,FALSE) -> 550 | Q88: =VLOOKUP(B88,sales,2,FALSE) -> Summer Sewald | R88: =VLOOKUP(B88,sales,3,FALSE) -> West
A89: PFFHM7HR | B89: Markita Hansen | C89: MG Advanced | D89: Opentech | E89: Engaging | F89: 42701 | I89: =VLOOKUP(pipeline!D89,account,2,FALSE) -> finance | J89: =VLOOKUP(D89,account,3,FALSE) -> 1994 | K89: =VLOOKUP(D89,account,4,FALSE) -> 355.23 | L89: =VLOOKUP(D89,account,5,FALSE) -> 853 | M89: =VLOOKUP(D89,account,6,FALSE) -> United States | N89: =VLOOKUP(D89,accounts,7,FALSE) -> 0 | O89: =VLOOKUP(C89,products,2,FALSE) -> MG | P89: =VLOOKUP(C89,products,3,FALSE) -> 3393 | Q89: =VLOOKUP(B89,sales,2,FALSE) -> Celia Rouche | R89: =VLOOKUP(B89,sales,3,FALSE) -> West
A90: IT10CFQH | B90: Rosalina Dieter | C90: GTX Basic | D90: Konex | E90: Won | F90: 42701 | G90: 42820 | H90: 538 | I90: =VLOOKUP(pipeline!D90,account,2,FALSE) -> technolgy | J90: =VLOOKUP(D90,account,3,FALSE) -> 1980 | K90: =VLOOKUP(D90,account,4,FALSE) -> 7708.38 | L90: =VLOOKUP(D90,account,5,FALSE) -> 13756 | M90: =VLOOKUP(D90,account,6,FALSE) -> United States | N90: =VLOOKUP(D90,accounts,7,FALSE) -> 0 | O90: =VLOOKUP(C90,products,2,FALSE) -> GTX | P90: =VLOOKUP(C90,products,3,FALSE) -> 550 | Q90: =VLOOKUP(B90,sales,2,FALSE) -> Celia Rouche | R90: =VLOOKUP(B90,sales,3,FALSE) -> West
A91: 2XQAKBXH | B91: Zane Levy | C91: GTX Plus Pro | D91: Doncon | E91: Won | F91: 42701 | G91: 42805 | H91: 5370 | I91: =VLOOKUP(pipeline!D91,account,2,FALSE) -> technolgy | J91: =VLOOKUP(D91,account,3,FALSE) -> 2010 | K91: =VLOOKUP(D91,account,4,FALSE) -> 587.72 | L91: =VLOOKUP(D91,account,5,FALSE) -> 1501 | M91: =VLOOKUP(D91,account,6,FALSE) -> United States | N91: =VLOOKUP(D91,accounts,7,FALSE) -> 0 | O91: =VLOOKUP(C91,products,2,FALSE) -> GTX | P91: =VLOOKUP(C91,products,3,FALSE) -> 5482 | Q91: =VLOOKUP(B91,sales,2,FALSE) -> Summer Sewald | R91: =VLOOKUP(B91,sales,3,FALSE) -> West
A92: 7G7YLGJO | B92: Zane Levy | C92: GTX Plus Pro | D92: Hatfan | E92: Won | F92: 42701 | G92: 42815 | H92: 6499 | I92: =VLOOKUP(pipeline!D92,account,2,FALSE) -> services | J92: =VLOOKUP(D92,account,3,FALSE) -> 1982 | K92: =VLOOKUP(D92,account,4,FALSE) -> 792.46 | L92: =VLOOKUP(D92,account,5,FALSE) -> 1299 | M92: =VLOOKUP(D92,account,6,FALSE) -> United States | N92: =VLOOKUP(D92,accounts,7,FALSE) -> 0 | O92: =VLOOKUP(C92,products,2,FALSE) -> GTX | P92: =VLOOKUP(C92,products,3,FALSE) -> 5482 | Q92: =VLOOKUP(B92,sales,2,FALSE) -> Summer Sewald | R92: =VLOOKUP(B92,sales,3,FALSE) -> West
A93: GCA97W27 | B93: Darcel Schlecht | C93: GTX Plus Basic | D93: Genco Pura Olive Oil Company | E93: Won | F93: 42702 | G93: 42800 | H93: 1161 | I93: =VLOOKUP(pipeline!D93,account,2,FALSE) -> retail | J93: =VLOOKUP(D93,account,3,FALSE) -> 2007 | K93: =VLOOKUP(D93,account,4,FALSE) -> 894.33 | L93: =VLOOKUP(D93,account,5,FALSE) -> 1635 | M93: =VLOOKUP(D93,account,6,FALSE) -> Italy | N93: =VLOOKUP(D93,accounts,7,FALSE) -> 0 | O93: =VLOOKUP(C93,products,2,FALSE) -> GTX | P93: =VLOOKUP(C93,products,3,FALSE) -> 1096 | Q93: =VLOOKUP(B93,sales,2,FALSE) -> Melvin Marxen | R93: =VLOOKUP(B93,sales,3,FALSE) -> Central
A94: K8FUZHOG | B94: Kary Hendrixson | C94: GTX Basic | D94: Scotfind | E94: Won | F94: 42702 | G94: 42820 | H94: 576 | I94: =VLOOKUP(pipeline!D94,account,2,FALSE) -> software | J94: =VLOOKUP(D94,account,3,FALSE) -> 1996 | K94: =VLOOKUP(D94,account,4,FALSE) -> 6354.87 | L94: =VLOOKUP(D94,account,5,FALSE) -> 16780 | M94: =VLOOKUP(D94,account,6,FALSE) -> United States | N94: =VLOOKUP(D94,accounts,7,FALSE) -> Bubba Gump | O94: =VLOOKUP(C94,products,2,FALSE) -> GTX | P94: =VLOOKUP(C94,products,3,FALSE) -> 550 | Q94: =VLOOKUP(B94,sales,2,FALSE) -> Summer Sewald | R94: =VLOOKUP(B94,sales,3,FALSE) -> West
A95: 5WJZMULK | B95: Maureen Marcano | C95: GTX Plus Basic | D95: Hatfan | E95: Won | F95: 42702 | G95: 42813 | H95: 979 | I95: =VLOOKUP(pipeline!D95,account,2,FALSE) -> services | J95: =VLOOKUP(D95,account,3,FALSE) -> 1982 | K95: =VLOOKUP(D95,account,4,FALSE) -> 792.46 | L95: =VLOOKUP(D95,account,5,FALSE) -> 1299 | M95: =VLOOKUP(D95,account,6,FALSE) -> United States | N95: =VLOOKUP(D95,accounts,7,FALSE) -> 0 | O95: =VLOOKUP(C95,products,2,FALSE) -> GTX | P95: =VLOOKUP(C95,products,3,FALSE) -> 1096 | Q95: =VLOOKUP(B95,sales,2,FALSE) -> Summer Sewald | R95: =VLOOKUP(B95,sales,3,FALSE) -> West
A96: ZPYD4T9W | B96: Versie Hillebrand | C96: MG Special | D96: Stanredtax | E96: Won | F96: 42702 | G96: 42801 | H96: 43 | I96: =VLOOKUP(pipeline!D96,account,2,FALSE) -> finance | J96: =VLOOKUP(D96,account,3,FALSE) -> 1987 | K96: =VLOOKUP(D96,account,4,FALSE) -> 1698.2 | L96: =VLOOKUP(D96,account,5,FALSE) -> 3798 | M96: =VLOOKUP(D96,account,6,FALSE) -> United States | N96: =VLOOKUP(D96,accounts,7,FALSE) -> 0 | O96: =VLOOKUP(C96,products,2,FALSE) -> MG | P96: =VLOOKUP(C96,products,3,FALSE) -> 55 | Q96: =VLOOKUP(B96,sales,2,FALSE) -> Dustin Brinkmann | R96: =VLOOKUP(B96,sales,3,FALSE) -> Central
A97: KE9ZEDS8 | B97: Gladys Colclough | C97: MG Special | D97: Scottech | E97: Won | F97: 42703 | G97: 42801 | H97: 57 | I97: =VLOOKUP(pipeline!D97,account,2,FALSE) -> marketing | J97: =VLOOKUP(D97,account,3,FALSE) -> 2012 | K97: =VLOOKUP(D97,account,4,FALSE) -> 45.39 | L97: =VLOOKUP(D97,account,5,FALSE) -> 100 | M97: =VLOOKUP(D97,account,6,FALSE) -> United States | N97: =VLOOKUP(D97,accounts,7,FALSE) -> Inity | O97: =VLOOKUP(C97,products,2,FALSE) -> MG | P97: =VLOOKUP(C97,products,3,FALSE) -> 55 | Q97: =VLOOKUP(B97,sales,2,FALSE) -> Melvin Marxen | R97: =VLOOKUP(B97,sales,3,FALSE) -> Central
A98: 7KK0HQ4C | B98: Lajuana Vencill | C98: MG Special | D98: Ron-tech | E98: Lost | F98: 42703 | G98: 42822 | H98: 0 | I98: =VLOOKUP(pipeline!D98,account,2,FALSE) -> medical | J98: =VLOOKUP(D98,account,3,FALSE) -> 1992 | K98: =VLOOKUP(D98,account,4,FALSE) -> 3922.42 | L98: =VLOOKUP(D98,account,5,FALSE) -> 6837 | M98: =VLOOKUP(D98,account,6,FALSE) -> United States | N98: =VLOOKUP(D98,accounts,7,FALSE) -> 0 | O98: =VLOOKUP(C98,products,2,FALSE) -> MG | P98: =VLOOKUP(C98,products,3,FALSE) -> 55 | Q98: =VLOOKUP(B98,sales,2,FALSE) -> Dustin Brinkmann | R98: =VLOOKUP(B98,sales,3,FALSE) -> Central
A99: FP7014Z0 | B99: Lajuana Vencill | C99: GTX Plus Basic | D99: Funholding | E99: Won | F99: 42703 | G99: 42806 | H99: 948 | I99: =VLOOKUP(pipeline!D99,account,2,FALSE) -> finance | J99: =VLOOKUP(D99,account,3,FALSE) -> 1991 | K99: =VLOOKUP(D99,account,4,FALSE) -> 2819.5 | L99: =VLOOKUP(D99,account,5,FALSE) -> 7227 | M99: =VLOOKUP(D99,account,6,FALSE) -> United States | N99: =VLOOKUP(D99,accounts,7,FALSE) -> Golddex | O99: =VLOOKUP(C99,products,2,FALSE) -> GTX | P99: =VLOOKUP(C99,products,3,FALSE) -> 1096 | Q99: =VLOOKUP(B99,sales,2,FALSE) -> Dustin Brinkmann | R99: =VLOOKUP(B99,sales,3,FALSE) -> Central
A100: N4HFHDMW | B100: Wilburn Farren | C100: MG Advanced | D100: Plussunin | E100: Won | F100: 42703 | G100: 42804 | H100: 3012 | I100: =VLOOKUP(pipeline!D100,account,2,FALSE) -> retail | J100: =VLOOKUP(D100,account,3,FALSE) -> 2003 | K100: =VLOOKUP(D100,account,4,FALSE) -> 1419.98 | L100: =VLOOKUP(D100,account,5,FALSE) -> 4018 | M100: =VLOOKUP(D100,account,6,FALSE) -> United States | N100: =VLOOKUP(D100,accounts,7,FALSE) -> 0 | O100: =VLOOKUP(C100,products,2,FALSE) -> MG | P100: =VLOOKUP(C100,products,3,FALSE) -> 3393 | Q100: =VLOOKUP(B100,sales,2,FALSE) -> Cara Losch | R100: =VLOOKUP(B100,sales,3,FALSE) -> East
A101: 2HFLKREC | B101: Cassey Cress | C101: MG Advanced | D101: Zotware | E101: Won | F101: 42704 | G101: 42809 | H101: 3665 | I101: =VLOOKUP(pipeline!D101,account,2,FALSE) -> software | J101: =VLOOKUP(D101,account,3,FALSE) -> 1979 | K101: =VLOOKUP(D101,account,4,FALSE) -> 4478.47 | L101: =VLOOKUP(D101,account,5,FALSE) -> 13809 | M101: =VLOOKUP(D101,account,6,FALSE) -> United States | N101: =VLOOKUP(D101,accounts,7,FALSE) -> 0 | O101: =VLOOKUP(C101,products,2,FALSE) -> MG | P101: =VLOOKUP(C101,products,3,FALSE) -> 3393 | Q101: =VLOOKUP(B101,sales,2,FALSE) -> Rocco Neubert | R101: =VLOOKUP(B101,sales,3,FALSE) -> East
... A171: F57JWIDF | B171: Gladys Colclough | C171: GTX Plus Basic | D171: Konmatfix | E171: Won | F171: 42718 | G171: 42796 | H171: 970 | I171: =VLOOKUP(pipeline!D171,account,2,FALSE) -> marketing | J171: =VLOOKUP(D171,account,3,FALSE) -> 1985 | K171: =VLOOKUP(D171,account,4,FALSE) -> 375.43 | L171: =VLOOKUP(D171,account,5,FALSE) -> 1190 | M171: =VLOOKUP(D171,account,6,FALSE) -> United States | N171: =VLOOKUP(D171,accounts,7,FALSE) -> 0 | O171: =VLOOKUP(C171,products,2,FALSE) -> GTX | P171: =VLOOKUP(C171,products,3,FALSE) -> 1096 | Q171: =VLOOKUP(B171,sales,2,FALSE) -> Melvin Marxen | R171: =VLOOKUP(B171,sales,3,FALSE) -> Central
A172: J53D8EOL | B172: Kary Hendrixson | C172: GTX Plus Basic | D172: Hottechi | E172: Engaging | F172: 42718 | I172: =VLOOKUP(pipeline!D172,account,2,FALSE) -> technolgy | J172: =VLOOKUP(D172,account,3,FALSE) -> 1997 | K172: =VLOOKUP(D172,account,4,FALSE) -> 8170.38 | L172: =VLOOKUP(D172,account,5,FALSE) -> 16499 | M172: =VLOOKUP(D172,account,6,FALSE) -> Korea | N172: =VLOOKUP(D172,accounts,7,FALSE) -> 0 | O172: =VLOOKUP(C172,products,2,FALSE) -> GTX | P172: =VLOOKUP(C172,products,3,FALSE) -> 1096 | Q172: =VLOOKUP(B172,sales,2,FALSE) -> Summer Sewald | R172: =VLOOKUP(B172,sales,3,FALSE) -> West
A173: LF8JZ3Q5 | B173: Kary Hendrixson | C173: GTX Plus Basic | D173: Hatfan | E173: Won | F173: 42718 | G173: 42807 | H173: 1046 | I173: =VLOOKUP(pipeline!D173,account,2,FALSE) -> services | J173: =VLOOKUP(D173,account,3,FALSE) -> 1982 | K173: =VLOOKUP(D173,account,4,FALSE) -> 792.46 | L173: =VLOOKUP(D173,account,5,FALSE) -> 1299 | M173: =VLOOKUP(D173,account,6,FALSE) -> United States | N173: =VLOOKUP(D173,accounts,7,FALSE) -> 0 | O173: =VLOOKUP(C173,products,2,FALSE) -> GTX | P173: =VLOOKUP(C173,products,3,FALSE) -> 1096 | Q173: =VLOOKUP(B173,sales,2,FALSE) -> Summer Sewald | R173: =VLOOKUP(B173,sales,3,FALSE) -> West
A174: MRGBSMQ5 | B174: Kary Hendrixson | C174: GTX Plus Basic | D174: Sunnamplex | E174: Won | F174: 42718 | G174: 42808 | H174: 988 | I174: =VLOOKUP(pipeline!D174,account,2,FALSE) -> marketing | J174: =VLOOKUP(D174,account,3,FALSE) -> 2008 | K174: =VLOOKUP(D174,account,4,FALSE) -> 894.37 | L174: =VLOOKUP(D174,account,5,FALSE) -> 1593 | M174: =VLOOKUP(D174,account,6,FALSE) -> Poland | N174: =VLOOKUP(D174,accounts,7,FALSE) -> 0 | O174: =VLOOKUP(C174,products,2,FALSE) -> GTX | P174: =VLOOKUP(C174,products,3,FALSE) -> 1096 | Q174: =VLOOKUP(B174,sales,2,FALSE) -> Summer Sewald | R174: =VLOOKUP(B174,sales,3,FALSE) -> West
A175: CBAV8ZJL | B175: Lajuana Vencill | C175: GTX Basic | D175: Codehow | E175: Won | F175: 42718 | G175: 42816 | H175: 547 | I175: =VLOOKUP(pipeline!D175,account,2,FALSE) -> software | J175: =VLOOKUP(D175,account,3,FALSE) -> 1998 | K175: =VLOOKUP(D175,account,4,FALSE) -> 2714.9 | L175: =VLOOKUP(D175,account,5,FALSE) -> 2641 | M175: =VLOOKUP(D175,account,6,FALSE) -> United States | N175: =VLOOKUP(D175,accounts,7,FALSE) -> Acme Corporation | O175: =VLOOKUP(C175,products,2,FALSE) -> GTX | P175: =VLOOKUP(C175,products,3,FALSE) -> 550 | Q175: =VLOOKUP(B175,sales,2,FALSE) -> Dustin Brinkmann | R175: =VLOOKUP(B175,sales,3,FALSE) -> Central
A176: 6JXHEZYK | B176: Versie Hillebrand | C176: MG Special | D176: Isdom | E176: Won | F176: 42718 | G176: 42825 | H176: 54 | I176: =VLOOKUP(pipeline!D176,account,2,FALSE) -> medical | J176: =VLOOKUP(D176,account,3,FALSE) -> 2002 | K176: =VLOOKUP(D176,account,4,FALSE) -> 3178.24 | L176: =VLOOKUP(D176,account,5,FALSE) -> 4540 | M176: =VLOOKUP(D176,account,6,FALSE) -> United States | N176: =VLOOKUP(D176,accounts,7,FALSE) -> 0 | O176: =VLOOKUP(C176,products,2,FALSE) -> MG | P176: =VLOOKUP(C176,products,3,FALSE) -> 55 | Q176: =VLOOKUP(B176,sales,2,FALSE) -> Dustin Brinkmann | R176: =VLOOKUP(B176,sales,3,FALSE) -> Central
A177: WDHNR2EI | B177: Violet Mclelland | C177: MG Special | D177: Silis | E177: Won | F177: 42718 | G177: 42814 | H177: 57 | I177: =VLOOKUP(pipeline!D177,account,2,FALSE) -> medical | J177: =VLOOKUP(D177,account,3,FALSE) -> 1994 | K177: =VLOOKUP(D177,account,4,FALSE) -> 2818.38 | L177: =VLOOKUP(D177,account,5,FALSE) -> 6290 | M177: =VLOOKUP(D177,account,6,FALSE) -> United States | N177: =VLOOKUP(D177,accounts,7,FALSE) -> 0 | O177: =VLOOKUP(C177,products,2,FALSE) -> MG | P177: =VLOOKUP(C177,products,3,FALSE) -> 55 | Q177: =VLOOKUP(B177,sales,2,FALSE) -> Cara Losch | R177: =VLOOKUP(B177,sales,3,FALSE) -> East
A178: 4K750D6F | B178: Violet Mclelland | C178: MG Special | D178: Yearin | E178: Won | F178: 42718 | G178: 42812 | H178: 55 | I178: =VLOOKUP(pipeline!D178,account,2,FALSE) -> retail | J178: =VLOOKUP(D178,account,3,FALSE) -> 2005 | K178: =VLOOKUP(D178,account,4,FALSE) -> 2261.05 | L178: =VLOOKUP(D178,account,5,FALSE) -> 3851 | M178: =VLOOKUP(D178,account,6,FALSE) -> United States | N178: =VLOOKUP(D178,accounts,7,FALSE) -> 0 | O178: =VLOOKUP(C178,products,2,FALSE) -> MG | P178: =VLOOKUP(C178,products,3,FALSE) -> 55 | Q178: =VLOOKUP(B178,sales,2,FALSE) -> Cara Losch | R178: =VLOOKUP(B178,sales,3,FALSE) -> East
A179: 94GI0ZJ7 | B179: Anna Snelling | C179: GTX Plus Pro | D179: Stanredtax | E179: Won | F179: 42719 | G179: 42809 | H179: 5765 | I179: =VLOOKUP(pipeline!D179,account,2,FALSE) -> finance | J179: =VLOOKUP(D179,account,3,FALSE) -> 1987 | K179: =VLOOKUP(D179,account,4,FALSE) -> 1698.2 | L179: =VLOOKUP(D179,account,5,FALSE) -> 3798 | M179: =VLOOKUP(D179,account,6,FALSE) -> United States | N179: =VLOOKUP(D179,accounts,7,FALSE) -> 0 | O179: =VLOOKUP(C179,products,2,FALSE) -> GTX | P179: =VLOOKUP(C179,products,3,FALSE) -> 5482 | Q179: =VLOOKUP(B179,sales,2,FALSE) -> Dustin Brinkmann | R179: =VLOOKUP(B179,sales,3,FALSE) -> Central
A180: TODG6DEK | B180: Daniell Hammack | C180: GTX Basic | D180: Bioplex | E180: Won | F180: 42719 | G180: 42810 | H180: 639 | I180: =VLOOKUP(pipeline!D180,account,2,FALSE) -> medical | J180: =VLOOKUP(D180,account,3,FALSE) -> 1991 | K180: =VLOOKUP(D180,account,4,FALSE) -> 326.82 | L180: =VLOOKUP(D180,account,5,FALSE) -> 1016 | M180: =VLOOKUP(D180,account,6,FALSE) -> United States | N180: =VLOOKUP(D180,accounts,7,FALSE) -> 0 | O180: =VLOOKUP(C180,products,2,FALSE) -> GTX | P180: =VLOOKUP(C180,products,3,FALSE) -> 550 | Q180: =VLOOKUP(B180,sales,2,FALSE) -> Rocco Neubert | R180: =VLOOKUP(B180,sales,3,FALSE) -> East
A181: EZVKSQ9C | B181: Boris Faz | C181: GTX Plus Pro | D181: Genco Pura Olive Oil Company | E181: Engaging | F181: 42720 | I181: =VLOOKUP(pipeline!D181,account,2,FALSE) -> retail | J181: =VLOOKUP(D181,account,3,FALSE) -> 2007 | K181: =VLOOKUP(D181,account,4,FALSE) -> 894.33 | L181: =VLOOKUP(D181,account,5,FALSE) -> 1635 | M181: =VLOOKUP(D181,account,6,FALSE) -> Italy | N181: =VLOOKUP(D181,accounts,7,FALSE) -> 0 | O181: =VLOOKUP(C181,products,2,FALSE) -> GTX | P181: =VLOOKUP(C181,products,3,FALSE) -> 5482 | Q181: =VLOOKUP(B181,sales,2,FALSE) -> Rocco Neubert | R181: =VLOOKUP(B181,sales,3,FALSE) -> East
A182: RJYG004O | B182: Daniell Hammack | C182: GTX Basic | D182: Domzoom | E182: Engaging | F182: 42720 | I182: =VLOOKUP(pipeline!D182,account,2,FALSE) -> entertainment | J182: =VLOOKUP(D182,account,3,FALSE) -> 1998 | K182: =VLOOKUP(D182,account,4,FALSE) -> 217.87 | L182: =VLOOKUP(D182,account,5,FALSE) -> 551 | M182: =VLOOKUP(D182,account,6,FALSE) -> United States | N182: =VLOOKUP(D182,accounts,7,FALSE) -> 0 | O182: =VLOOKUP(C182,products,2,FALSE) -> GTX | P182: =VLOOKUP(C182,products,3,FALSE) -> 550 | Q182: =VLOOKUP(B182,sales,2,FALSE) -> Rocco Neubert | R182: =VLOOKUP(B182,sales,3,FALSE) -> East
A183: JZOKHHWN | B183: Donn Cantrell | C183: GTX Plus Basic | D183: Opentech | E183: Won | F183: 42720 | G183: 42801 | H183: 1037 | I183: =VLOOKUP(pipeline!D183,account,2,FALSE) -> finance | J183: =VLOOKUP(D183,account,3,FALSE) -> 1994 | K183: =VLOOKUP(D183,account,4,FALSE) -> 355.23 | L183: =VLOOKUP(D183,account,5,FALSE) -> 853 | M183: =VLOOKUP(D183,account,6,FALSE) -> United States | N183: =VLOOKUP(D183,accounts,7,FALSE) -> 0 | O183: =VLOOKUP(C183,products,2,FALSE) -> GTX | P183: =VLOOKUP(C183,products,3,FALSE) -> 1096 | Q183: =VLOOKUP(B183,sales,2,FALSE) -> Rocco Neubert | R183: =VLOOKUP(B183,sales,3,FALSE) -> East
A184: EH6I67I0 | B184: James Ascencio | C184: GTX Basic | D184: Plexzap | E184: Won | F184: 42720 | G184: 42809 | H184: 537 | I184: =VLOOKUP(pipeline!D184,account,2,FALSE) -> retail | J184: =VLOOKUP(D184,account,3,FALSE) -> 2001 | K184: =VLOOKUP(D184,account,4,FALSE) -> 2437.85 | L184: =VLOOKUP(D184,account,5,FALSE) -> 4874 | M184: =VLOOKUP(D184,account,6,FALSE) -> United States | N184: =VLOOKUP(D184,accounts,7,FALSE) -> 0 | O184: =VLOOKUP(C184,products,2,FALSE) -> GTX | P184: =VLOOKUP(C184,products,3,FALSE) -> 550 | Q184: =VLOOKUP(B184,sales,2,FALSE) -> Summer Sewald | R184: =VLOOKUP(B184,sales,3,FALSE) -> West
A185: OT87JDWO | B185: Lajuana Vencill | C185: GTX Basic | D185: Konmatfix | E185: Won | F185: 42720 | G185: 42818 | H185: 560 | I185: =VLOOKUP(pipeline!D185,account,2,FALSE) -> marketing | J185: =VLOOKUP(D185,account,3,FALSE) -> 1985 | K185: =VLOOKUP(D185,account,4,FALSE) -> 375.43 | L185: =VLOOKUP(D185,account,5,FALSE) -> 1190 | M185: =VLOOKUP(D185,account,6,FALSE) -> United States | N185: =VLOOKUP(D185,accounts,7,FALSE) -> 0 | O185: =VLOOKUP(C185,products,2,FALSE) -> GTX | P185: =VLOOKUP(C185,products,3,FALSE) -> 550 | Q185: =VLOOKUP(B185,sales,2,FALSE) -> Dustin Brinkmann | R185: =VLOOKUP(B185,sales,3,FALSE) -> Central
A186: YHKT6YJ7 | B186: Moses Frase | C186: GTX Basic | D186: dambase | E186: Won | F186: 42720 | G186: 42807 | H186: 589 | I186: =VLOOKUP(pipeline!D186,account,2,FALSE) -> marketing | J186: =VLOOKUP(D186,account,3,FALSE) -> 1995 | K186: =VLOOKUP(D186,account,4,FALSE) -> 2173.98 | L186: =VLOOKUP(D186,account,5,FALSE) -> 2928 | M186: =VLOOKUP(D186,account,6,FALSE) -> United States | N186: =VLOOKUP(D186,accounts,7,FALSE) -> Inity | O186: =VLOOKUP(C186,products,2,FALSE) -> GTX | P186: =VLOOKUP(C186,products,3,FALSE) -> 550 | Q186: =VLOOKUP(B186,sales,2,FALSE) -> Dustin Brinkmann | R186: =VLOOKUP(B186,sales,3,FALSE) -> Central
A187: H78I3TAY | B187: Reed Clapper | C187: GTX Basic | D187: Mathtouch | E187: Won | F187: 42720 | G187: 42808 | H187: 493 | I187: =VLOOKUP(pipeline!D187,account,2,FALSE) -> marketing | J187: =VLOOKUP(D187,account,3,FALSE) -> 1984 | K187: =VLOOKUP(D187,account,4,FALSE) -> 3027.46 | L187: =VLOOKUP(D187,account,5,FALSE) -> 9516 | M187: =VLOOKUP(D187,account,6,FALSE) -> Jordan | N187: =VLOOKUP(D187,accounts,7,FALSE) -> 0 | O187: =VLOOKUP(C187,products,2,FALSE) -> GTX | P187: =VLOOKUP(C187,products,3,FALSE) -> 550 | Q187: =VLOOKUP(B187,sales,2,FALSE) -> Rocco Neubert | R187: =VLOOKUP(B187,sales,3,FALSE) -> East
A188: 1ROC43JK | B188: Versie Hillebrand | C188: MG Special | D188: Betatech | E188: Won | F188: 42720 | G188: 42802 | H188: 50 | I188: =VLOOKUP(pipeline!D188,account,2,FALSE) -> medical | J188: =VLOOKUP(D188,account,3,FALSE) -> 1986 | K188: =VLOOKUP(D188,account,4,FALSE) -> 647.18 | L188: =VLOOKUP(D188,account,5,FALSE) -> 1185 | M188: =VLOOKUP(D188,account,6,FALSE) -> Kenya | N188: =VLOOKUP(D188,accounts,7,FALSE) -> 0 | O188: =VLOOKUP(C188,products,2,FALSE) -> MG | P188: =VLOOKUP(C188,products,3,FALSE) -> 55 | Q188: =VLOOKUP(B188,sales,2,FALSE) -> Dustin Brinkmann | R188: =VLOOKUP(B188,sales,3,FALSE) -> Central
A189: LPZLQL48 | B189: Vicki Laflamme | C189: GTX Basic | D189: Y-corporation | E189: Won | F189: 42720 | G189: 42822 | H189: 492 | I189: =VLOOKUP(pipeline!D189,account,2,FALSE) -> employment | J189: =VLOOKUP(D189,account,3,FALSE) -> 1983 | K189: =VLOOKUP(D189,account,4,FALSE) -> 2871.35 | L189: =VLOOKUP(D189,account,5,FALSE) -> 9561 | M189: =VLOOKUP(D189,account,6,FALSE) -> United States | N189: =VLOOKUP(D189,accounts,7,FALSE) -> 0 | O189: =VLOOKUP(C189,products,2,FALSE) -> GTX | P189: =VLOOKUP(C189,products,3,FALSE) -> 550 | Q189: =VLOOKUP(B189,sales,2,FALSE) -> Celia Rouche | R189: =VLOOKUP(B189,sales,3,FALSE) -> West
A190: 3KR50X38 | B190: Corliss Cosme | C190: GTX Plus Basic | D190: Konex | E190: Won | F190: 42721 | G190: 42807 | H190: 1255 | I190: =VLOOKUP(pipeline!D190,account,2,FALSE) -> technolgy | J190: =VLOOKUP(D190,account,3,FALSE) -> 1980 | K190: =VLOOKUP(D190,account,4,FALSE) -> 7708.38 | L190: =VLOOKUP(D190,account,5,FALSE) -> 13756 | M190: =VLOOKUP(D190,account,6,FALSE) -> United States | N190: =VLOOKUP(D190,accounts,7,FALSE) -> 0 | O190: =VLOOKUP(C190,products,2,FALSE) -> GTX | P190: =VLOOKUP(C190,products,3,FALSE) -> 1096 | Q190: =VLOOKUP(B190,sales,2,FALSE) -> Cara Losch | R190: =VLOOKUP(B190,sales,3,FALSE) -> East
A191: Q3WLHRE9 | B191: Darcel Schlecht | C191: GTX Basic | D191: Statholdings | E191: Won | F191: 42721 | G191: 42798 | H191: 463 | I191: =VLOOKUP(pipeline!D191,account,2,FALSE) -> employment | J191: =VLOOKUP(D191,account,3,FALSE) -> 1997 | K191: =VLOOKUP(D191,account,4,FALSE) -> 291.27 | L191: =VLOOKUP(D191,account,5,FALSE) -> 586 | M191: =VLOOKUP(D191,account,6,FALSE) -> United States | N191: =VLOOKUP(D191,accounts,7,FALSE) -> 0 | O191: =VLOOKUP(C191,products,2,FALSE) -> GTX | P191: =VLOOKUP(C191,products,3,FALSE) -> 550 | Q191: =VLOOKUP(B191,sales,2,FALSE) -> Melvin Marxen | R191: =VLOOKUP(B191,sales,3,FALSE) -> Central
A192: IX7UEOAP | B192: Donn Cantrell | C192: GTX Plus Basic | D192: Initech | E192: Lost | F192: 42721 | G192: 42821 | H192: 0 | I192: =VLOOKUP(pipeline!D192,account,2,FALSE) -> telecommunications | J192: =VLOOKUP(D192,account,3,FALSE) -> 1994 | K192: =VLOOKUP(D192,account,4,FALSE) -> 6395.05 | L192: =VLOOKUP(D192,account,5,FALSE) -> 20275 | M192: =VLOOKUP(D192,account,6,FALSE) -> United States | N192: =VLOOKUP(D192,accounts,7,FALSE) -> 0 | O192: =VLOOKUP(C192,products,2,FALSE) -> GTX | P192: =VLOOKUP(C192,products,3,FALSE) -> 1096 | Q192: =VLOOKUP(B192,sales,2,FALSE) -> Rocco Neubert | R192: =VLOOKUP(B192,sales,3,FALSE) -> East
A193: NQU62K1H | B193: Donn Cantrell | C193: GTX Basic | D193: Zencorporation | E193: Won | F193: 42721 | G193: 42806 | H193: 605 | I193: =VLOOKUP(pipeline!D193,account,2,FALSE) -> technolgy | J193: =VLOOKUP(D193,account,3,FALSE) -> 2011 | K193: =VLOOKUP(D193,account,4,FALSE) -> 40.79 | L193: =VLOOKUP(D193,account,5,FALSE) -> 142 | M193: =VLOOKUP(D193,account,6,FALSE) -> China | N193: =VLOOKUP(D193,accounts,7,FALSE) -> 0 | O193: =VLOOKUP(C193,products,2,FALSE) -> GTX | P193: =VLOOKUP(C193,products,3,FALSE) -> 550 | Q193: =VLOOKUP(B193,sales,2,FALSE) -> Rocco Neubert | R193: =VLOOKUP(B193,sales,3,FALSE) -> East
A194: NAQKOU0T | B194: Hayden Neloms | C194: GTX Plus Basic | D194: Fasehatice | E194: Won | F194: 42721 | G194: 42814 | H194: 1315 | I194: =VLOOKUP(pipeline!D194,account,2,FALSE) -> retail | J194: =VLOOKUP(D194,account,3,FALSE) -> 1990 | K194: =VLOOKUP(D194,account,4,FALSE) -> 4968.91 | L194: =VLOOKUP(D194,account,5,FALSE) -> 7523 | M194: =VLOOKUP(D194,account,6,FALSE) -> United States | N194: =VLOOKUP(D194,accounts,7,FALSE) -> 0 | O194: =VLOOKUP(C194,products,2,FALSE) -> GTX | P194: =VLOOKUP(C194,products,3,FALSE) -> 1096 | Q194: =VLOOKUP(B194,sales,2,FALSE) -> Celia Rouche | R194: =VLOOKUP(B194,sales,3,FALSE) -> West
... A204: RNTOJ78L | B204: Rosalina Dieter | C204: MG Special | D204: Hatfan | E204: Lost | F204: 42722 | G204: 42807 | H204: 0 | I204: =VLOOKUP(pipeline!D204,account,2,FALSE) -> services | J204: =VLOOKUP(D204,account,3,FALSE) -> 1982 | K204: =VLOOKUP(D204,account,4,FALSE) -> 792.46 | L204: =VLOOKUP(D204,account,5,FALSE) -> 1299 | M204: =VLOOKUP(D204,account,6,FALSE) -> United States | N204: =VLOOKUP(D204,accounts,7,FALSE) -> 0 | O204: =VLOOKUP(C204,products,2,FALSE) -> MG | P204: =VLOOKUP(C204,products,3,FALSE) -> 55 | Q204: =VLOOKUP(B204,sales,2,FALSE) -> Celia Rouche | R204: =VLOOKUP(B204,sales,3,FALSE) -> West
...

Sheet accounts
A1: account | B1: sector | C1: year_established | D1: revenue | E1: employees | F1: office_location | G1: subsidiary_of
A2: Acme Corporation | B2: technolgy | C2: 1996 | D2: 1100.04 | E2: 2822 | F2: United States
A3: Betasoloin | B3: medical | C3: 1999 | D3: 251.41 | E3: 495 | F3: United States
A4: Betatech | B4: medical | C4: 1986 | D4: 647.18 | E4: 1185 | F4: Kenya
A5: Bioholding | B5: medical | C5: 2012 | D5: 587.34 | E5: 1356 | F5: Philipines
A6: Bioplex | B6: medical | C6: 1991 | D6: 326.82 | E6: 1016 | F6: United States
A7: Blackzim | B7: retail | C7: 2009 | D7: 497.11 | E7: 1588 | F7: United States
A8: Bluth Company | B8: technolgy | C8: 1993 | D8: 1242.32 | E8: 3027 | F8: United States | G8: Acme Corporation
A9: Bubba Gump | B9: software | C9: 2002 | D9: 987.39 | E9: 2253 | F9: United States
A10: Cancity | B10: retail | C10: 2001 | D10: 718.62 | E10: 2448 | F10: United States
A11: Cheers | B11: entertainment | C11: 1993 | D11: 4269.9 | E11: 6472 | F11: United States | G11: Massive Dynamic
A12: Codehow | B12: software | C12: 1998 | D12: 2714.9 | E12: 2641 | F12: United States | G12: Acme Corporation
A13: Condax | B13: medical | C13: 2017 | D13: 4.54 | E13: 9 | F13: United States
A14: Conecom | B14: technolgy | C14: 2005 | D14: 1520.66 | E14: 1806 | F14: United States
A15: Dalttechnology | B15: software | C15: 2013 | D15: 98.79 | E15: 96 | F15: United States | G15: Bubba Gump
A16: dambase | B16: marketing | C16: 1995 | D16: 2173.98 | E16: 2928 | F16: United States | G16: Inity
A17: Domzoom | B17: entertainment | C17: 1998 | D17: 217.87 | E17: 551 | F17: United States
A18: Doncon | B18: technolgy | C18: 2010 | D18: 587.72 | E18: 1501 | F18: United States
A19: Donquadtech | B19: technolgy | C19: 1992 | D19: 1712.68 | E19: 3194 | F19: United States | G19: Acme Corporation
A20: Dontechi | B20: software | C20: 1982 | D20: 4618 | E20: 10083 | F20: United States
A21: Donware | B21: marketing | C21: 1999 | D21: 1197.44 | E21: 2570 | F21: United States
A22: Fasehatice | B22: retail | C22: 1990 | D22: 4968.91 | E22: 7523 | F22: United States
A23: Faxquote | B23: telecommunications | C23: 1995 | D23: 1825.82 | E23: 5595 | F23: United States | G23: Sonron
A24: Finhigh | B24: finance | C24: 2006 | D24: 1102.43 | E24: 1759 | F24: United States
A25: Finjob | B25: employment | C25: 1988 | D25: 2059.9 | E25: 3644 | F25: United States
A26: Funholding | B26: finance | C26: 1991 | D26: 2819.5 | E26: 7227 | F26: United States | G26: Golddex
A27: Ganjaflex | B27: retail | C27: 1995 | D27: 5158.71 | E27: 17479 | F27: Japan
A28: Gekko & Co | B28: retail | C28: 1990 | D28: 2520.83 | E28: 3502 | F28: United States
A29: Genco Pura Olive Oil Company | B29: retail | C29: 2007 | D29: 894.33 | E29: 1635 | F29: Italy
A30: Globex Corporation | B30: technolgy | C30: 2000 | D30: 1223.72 | E30: 2497 | F30: Norway
A31: Gogozoom | B31: telecommunications | C31: 2007 | D31: 86.68 | E31: 187 | F31: United States | G31: Sonron
A32: Golddex | B32: finance | C32: 2008 | D32: 52.5 | E32: 165 | F32: United States
A33: Goodsilron | B33: marketing | C33: 2000 | D33: 2952.73 | E33: 5107 | F33: United States
A34: Green-Plus | B34: services | C34: 2003 | D34: 692.19 | E34: 1922 | F34: United States
A35: Groovestreet | B35: retail | C35: 2003 | D35: 223.8 | E35: 299 | F35: United States
A36: Hatfan | B36: services | C36: 1982 | D36: 792.46 | E36: 1299 | F36: United States
A37: Hottechi | B37: technolgy | C37: 1997 | D37: 8170.38 | E37: 16499 | F37: Korea
A38: Initech | B38: telecommunications | C38: 1994 | D38: 6395.05 | E38: 20275 | F38: United States
A39: Inity | B39: marketing | C39: 1986 | D39: 2403.58 | E39: 8801 | F39: United States
A40: Isdom | B40: medical | C40: 2002 | D40: 3178.24 | E40: 4540 | F40: United States
A41: Iselectrics | B41: technolgy | C41: 2011 | D41: 527.11 | E41: 1428 | F41: United States | G41: Acme Corporation
A42: J-Texon | B42: retail | C42: 1989 | D42: 1388.67 | E42: 3583 | F42: United States
A43: Kan-code | B43: software | C43: 1982 | D43: 11698.03 | E43: 34288 | F43: United States
A44: Kinnamplus | B44: retail | C44: 2004 | D44: 702.72 | E44: 1831 | F44: United States
A45: Konex | B45: technolgy | C45: 1980 | D45: 7708.38 | E45: 13756 | F45: United States
A46: Konmatfix | B46: marketing | C46: 1985 | D46: 375.43 | E46: 1190 | F46: United States
A47: Labdrill | B47: medical | C47: 1985 | D47: 2741.37 | E47: 9226 | F47: United States
A48: Lexiqvolax | B48: medical | C48: 2004 | D48: 1618.89 | E48: 3889 | F48: United States
A49: Massive Dynamic | B49: entertainment | C49: 1989 | D49: 665.06 | E49: 1095 | F49: United States
A50: Mathtouch | B50: marketing | C50: 1984 | D50: 3027.46 | E50: 9516 | F50: Jordan
A51: Nam-zim | B51: services | C51: 1987 | D51: 405.59 | E51: 1179 | F51: Brazil | G51: Warephase
A52: Newex | B52: services | C52: 1991 | D52: 1012.72 | E52: 3492 | F52: Germany
A53: Ontomedia | B53: employment | C53: 1997 | D53: 882.12 | E53: 2769 | F53: United States
A54: Opentech | B54: finance | C54: 1994 | D54: 355.23 | E54: 853 | F54: United States
A55: Plexzap | B55: retail | C55: 2001 | D55: 2437.85 | E55: 4874 | F55: United States
A56: Plusstrip | B56: entertainment | C56: 2002 | D56: 349.81 | E56: 315 | F56: United States
A57: Plussunin | B57: retail | C57: 2003 | D57: 1419.98 | E57: 4018 | F57: United States
A58: Rangreen | B58: technolgy | C58: 1987 | D58: 2938.67 | E58: 8775 | F58: Panama
A59: Rantouch | B59: telecommunications | C59: 1994 | D59: 1188.42 | E59: 3015 | F59: United States
A60: Ron-tech | B60: medical | C60: 1992 | D60: 3922.42 | E60: 6837 | F60: United States
A61: Rundofase | B61: technolgy | C61: 1983 | D61: 1008.06 | E61: 1238 | F61: United States
A62: Scotfind | B62: software | C62: 1996 | D62: 6354.87 | E62: 16780 | F62: United States | G62: Bubba Gump
A63: Scottech | B63: marketing | C63: 2012 | D63: 45.39 | E63: 100 | F63: United States | G63: Inity
A64: Silis | B64: medical | C64: 1994 | D64: 2818.38 | E64: 6290 | F64: United States
A65: Singletechno | B65: retail | C65: 1996 | D65: 2214.94 | E65: 5374 | F65: United States
A66: Sonron | B66: telecommunications | C66: 1999 | D66: 1699.85 | E66: 5108 | F66: United States
A67: Stanredtax | B67: finance | C67: 1987 | D67: 1698.2 | E67: 3798 | F67: United States
A68: Statholdings | B68: employment | C68: 1997 | D68: 291.27 | E68: 586 | F68: United States
A69: Streethex | B69: retail | C69: 1988 | D69: 1376.8 | E69: 1165 | F69: Belgium
A70: Sumace | B70: retail | C70: 2000 | D70: 167.89 | E70: 493 | F70: Romania
A71: Sunnamplex | B71: marketing | C71: 2008 | D71: 894.37 | E71: 1593 | F71: Poland
A72: The New York Inquirer | B72: medical | C72: 1996 | D72: 439.21 | E72: 792 | F72: United States
A73: Toughzap | B73: retail | C73: 1995 | D73: 332.43 | E73: 799 | F73: United States
A74: Treequote | B74: telecommunications | C74: 1988 | D74: 5266.09 | E74: 8595 | F74: United States | G74: Sonron
A75: Umbrella Corporation | B75: finance | C75: 1998 | D75: 2022.14 | E75: 5113 | F75: United States
A76: Vehement Capital Partners | B76: finance | C76: 1993 | D76: 646.1 | E76: 883 | F76: United States | G76: Golddex
A77: Warephase | B77: services | C77: 1997 | D77: 2041.73 | E77: 5276 | F77: United States
A78: Xx-holding | B78: finance | C78: 1993 | D78: 7537.24 | E78: 20293 | F78: United States
A79: Xx-zobam | B79: entertainment | C79: 1989 | D79: 3838.39 | E79: 8274 | F79: United States
A80: Y-corporation | B80: employment | C80: 1983 | D80: 2871.35 | E80: 9561 | F80: United States
A81: Yearin | B81: retail | C81: 2005 | D81: 2261.05 | E81: 3851 | F81: United States
A82: Zathunicon | B82: retail | C82: 2010 | D82: 71.12 | E82: 144 | F82: United States
A83: Zencorporation | B83: technolgy | C83: 2011 | D83: 40.79 | E83: 142 | F83: China
A84: Zoomit | B84: entertainment | C84: 1992 | D84: 324.19 | E84: 978 | F84: United States
A85: Zotware | B85: software | C85: 1979 | D85: 4478.47 | E85: 13809 | F85: United States
A86: Zumgoity | B86: medical | C86: 1984 | D86: 441.08 | E86: 1210 | F86: United States

Sheet products
A1: product | B1: series | C1: sales_price
A2: GTX Basic | B2: GTX | C2: 550
A3: GTX Pro | B3: GTX | C3: 4821
A4: MG Special | B4: MG | C4: 55
A5: MG Advanced | B5: MG | C5: 3393
A6: GTX Plus Pro | B6: GTX | C6: 5482
A7: GTX Plus Basic | B7: GTX | C7: 1096
A8: GTK 500 | B8: GTK | C8: 26768

Sheet Table Field Description
A1: Table | B1: Field | C1: Description
A2: accounts | B2: account | C2: Company name
A3: accounts | B3: sector | C3: Industry
A4: accounts | B4: year_established | C4: Year Established
A5: accounts | B5: revenue | C5: Annual revenue (in millions of USD)
A6: accounts | B6: employees | C6: Number of employees
A7: accounts | B7: office_location | C7: Headquarters
A8: accounts | B8: subsidiary_of | C8: Parent company
A9: products | B9: product | C9: Product name
A10: products | B10: series | C10: Product series
A11: products | B11: sales_price | C11: Suggested retail price
A12: sales_teams | B12: sales_agent | C12: Sales agent
... A22: sales_pipeline | B22: close_value | C22: Revenue from the deal

Sheet sales teams
A1: sales_agent | B1: manager | C1: regional_office
A2: Anna Snelling | B2: Dustin Brinkmann | C2: Central
A3: Cecily Lampkin | B3: Dustin Brinkmann | C3: Central
A4: Versie Hillebrand | B4: Dustin Brinkmann | C4: Central
A5: Lajuana Vencill | B5: Dustin Brinkmann | C5: Central
A6: Moses Frase | B6: Dustin Brinkmann | C6: Central
A7: Jonathan Berthelot | B7: Melvin Marxen | C7: Central
A8: Marty Freudenburg | B8: Melvin Marxen | C8: Central
A9: Gladys Colclough | B9: Melvin Marxen | C9: Central
A10: Niesha Huffines | B10: Melvin Marxen | C10: Central
A11: Darcel Schlecht | B11: Melvin Marxen | C11: Central
A12: Mei-Mei Johns | B12: Melvin Marxen | C12: Central
... A36: Carl Lin | B36: Summer Sewald | C36: West
